{
"meta":{"test_sets":[],"test_metrics":[],"learn_metrics":[{"best_value":"Min","name":"Logloss"}],"launch_mode":"Train","parameters":"","iteration_count":1000,"learn_sets":["learn"],"name":"experiment"},
"iterations":[
{"learn":[0.6736047705],"iteration":0,"passed_time":0.05906580079,"remaining_time":59.00673499},
{"learn":[0.6574360167],"iteration":1,"passed_time":0.06042284198,"remaining_time":30.15099815},
{"learn":[0.6398882797],"iteration":2,"passed_time":0.06193097865,"remaining_time":20.58172857},
{"learn":[0.6233475599],"iteration":3,"passed_time":0.06325472188,"remaining_time":15.75042575},
{"learn":[0.6077596011],"iteration":4,"passed_time":0.06469703895,"remaining_time":12.87471075},
{"learn":[0.5930812206],"iteration":5,"passed_time":0.06615179462,"remaining_time":10.95914731},
{"learn":[0.5792575897],"iteration":6,"passed_time":0.06747876132,"remaining_time":9.572344285},
{"learn":[0.5662248236],"iteration":7,"passed_time":0.06872418346,"remaining_time":8.521798749},
{"learn":[0.5539353956],"iteration":8,"passed_time":0.07023261393,"remaining_time":7.733391157},
{"learn":[0.5423750778],"iteration":9,"passed_time":0.07171599614,"remaining_time":7.099883618},
{"learn":[0.5314744499],"iteration":10,"passed_time":0.07311312093,"remaining_time":6.573534236},
{"learn":[0.5212052607],"iteration":11,"passed_time":0.07447325135,"remaining_time":6.131631028},
{"learn":[0.5115276677],"iteration":12,"passed_time":0.07584476556,"remaining_time":5.75836797},
{"learn":[0.5024227225],"iteration":13,"passed_time":0.0773052467,"remaining_time":5.444498089},
{"learn":[0.493850725],"iteration":14,"passed_time":0.07864475479,"remaining_time":5.164338898},
{"learn":[0.4857766051],"iteration":15,"passed_time":0.08002349267,"remaining_time":4.921444799},
{"learn":[0.4781603782],"iteration":16,"passed_time":0.08146917322,"remaining_time":4.710835134},
{"learn":[0.4709903982],"iteration":17,"passed_time":0.0828250058,"remaining_time":4.518564205},
{"learn":[0.4642215746],"iteration":18,"passed_time":0.08421947249,"remaining_time":4.348384343},
{"learn":[0.4586648974],"iteration":19,"passed_time":0.08537581609,"remaining_time":4.183414988},
{"learn":[0.4525955398],"iteration":20,"passed_time":0.08670289863,"remaining_time":4.04200656},
{"learn":[0.4480041041],"iteration":21,"passed_time":0.08809541183,"remaining_time":3.916241489},
{"learn":[0.4432701232],"iteration":22,"passed_time":0.08959081954,"remaining_time":3.805662204},
{"learn":[0.4387899249],"iteration":23,"passed_time":0.09090041961,"remaining_time":3.696617064},
{"learn":[0.4338222887],"iteration":24,"passed_time":0.09231605903,"remaining_time":3.600326302},
{"learn":[0.4298175495],"iteration":25,"passed_time":0.09357367889,"remaining_time":3.505413971},
{"learn":[0.4253435699],"iteration":26,"passed_time":0.09488708737,"remaining_time":3.419449482},
{"learn":[0.4211192368],"iteration":27,"passed_time":0.09635201247,"remaining_time":3.34479129},
{"learn":[0.4171382497],"iteration":28,"passed_time":0.09768672372,"remaining_time":3.270820991},
{"learn":[0.413377083],"iteration":29,"passed_time":0.09915205272,"remaining_time":3.205916371},
{"learn":[0.4105012309],"iteration":30,"passed_time":0.1006003545,"remaining_time":3.144572373},
{"learn":[0.4070867241],"iteration":31,"passed_time":0.1020160726,"remaining_time":3.085986196},
{"learn":[0.40385353],"iteration":32,"passed_time":0.1035142976,"remaining_time":3.033282599},
{"learn":[0.4013895766],"iteration":33,"passed_time":0.1048517996,"remaining_time":2.97902466},
{"learn":[0.3984750151],"iteration":34,"passed_time":0.1062113789,"remaining_time":2.928399446},
{"learn":[0.3961236473],"iteration":35,"passed_time":0.1075753388,"remaining_time":2.880628517},
{"learn":[0.3938894688],"iteration":36,"passed_time":0.1087063672,"remaining_time":2.829303556},
{"learn":[0.3913547952],"iteration":37,"passed_time":0.1101231136,"remaining_time":2.787853559},
{"learn":[0.3889694525],"iteration":38,"passed_time":0.1115621067,"remaining_time":2.749004731},
{"learn":[0.3867042922],"iteration":39,"passed_time":0.1128185248,"remaining_time":2.707644596},
{"learn":[0.3845593833],"iteration":40,"passed_time":0.1139625959,"remaining_time":2.665612914},
{"learn":[0.3825238699],"iteration":41,"passed_time":0.1152584398,"remaining_time":2.628990128},
{"learn":[0.3809581417],"iteration":42,"passed_time":0.1163889259,"remaining_time":2.59033028},
{"learn":[0.379777238],"iteration":43,"passed_time":0.1175639268,"remaining_time":2.5543435},
{"learn":[0.3783448894],"iteration":44,"passed_time":0.1187646894,"remaining_time":2.520450631},
{"learn":[0.3768999577],"iteration":45,"passed_time":0.1201013633,"remaining_time":2.49079784},
{"learn":[0.3752455514],"iteration":46,"passed_time":0.1216674795,"remaining_time":2.467002298},
{"learn":[0.3740019589],"iteration":47,"passed_time":0.1229405333,"remaining_time":2.438320576},
{"learn":[0.3728175635],"iteration":48,"passed_time":0.1242090333,"remaining_time":2.410669197},
{"learn":[0.371614108],"iteration":49,"passed_time":0.1253995448,"remaining_time":2.382591351},
{"learn":[0.3704684009],"iteration":50,"passed_time":0.1266288219,"remaining_time":2.356289255},
{"learn":[0.3693853598],"iteration":51,"passed_time":0.1279035856,"remaining_time":2.331780752},
{"learn":[0.368111668],"iteration":52,"passed_time":0.1292484977,"remaining_time":2.309402402},
{"learn":[0.3671212767],"iteration":53,"passed_time":0.1306711936,"remaining_time":2.289165724},
{"learn":[0.365949093],"iteration":54,"passed_time":0.1319957584,"remaining_time":2.267927121},
{"learn":[0.3650881788],"iteration":55,"passed_time":0.1331831212,"remaining_time":2.2450869},
{"learn":[0.3640341056],"iteration":56,"passed_time":0.1346695857,"remaining_time":2.227954725},
{"learn":[0.3632526848],"iteration":57,"passed_time":0.1360151894,"remaining_time":2.209074283},
{"learn":[0.3622879992],"iteration":58,"passed_time":0.1376100886,"remaining_time":2.194764295},
{"learn":[0.3619851805],"iteration":59,"passed_time":0.1385341397,"remaining_time":2.170368189},
{"learn":[0.3610812271],"iteration":60,"passed_time":0.1397745636,"remaining_time":2.151611725},
{"learn":[0.360413715],"iteration":61,"passed_time":0.1410265374,"remaining_time":2.133595034},
{"learn":[0.3595836866],"iteration":62,"passed_time":0.1422885104,"remaining_time":2.116259273},
{"learn":[0.3589780992],"iteration":63,"passed_time":0.1434879313,"remaining_time":2.098510995},
{"learn":[0.3582167899],"iteration":64,"passed_time":0.145080541,"remaining_time":2.086927782},
{"learn":[0.3574840319],"iteration":65,"passed_time":0.146574062,"remaining_time":2.074245059},
{"learn":[0.3570823349],"iteration":66,"passed_time":0.1475318183,"remaining_time":2.05443562},
{"learn":[0.3565351795],"iteration":67,"passed_time":0.148671014,"remaining_time":2.037667426},
{"learn":[0.355892304],"iteration":68,"passed_time":0.1500755549,"remaining_time":2.024932488},
{"learn":[0.3554290012],"iteration":69,"passed_time":0.1512356287,"remaining_time":2.009273353},
{"learn":[0.3548378304],"iteration":70,"passed_time":0.1524895326,"remaining_time":1.995250363},
{"learn":[0.3543904621],"iteration":71,"passed_time":0.1536624619,"remaining_time":1.980538398},
{"learn":[0.3539624274],"iteration":72,"passed_time":0.1549600556,"remaining_time":1.967780433},
{"learn":[0.3535547042],"iteration":73,"passed_time":0.1561278532,"remaining_time":1.953708001},
{"learn":[0.3530519894],"iteration":74,"passed_time":0.1576614854,"remaining_time":1.944491653},
{"learn":[0.352691351],"iteration":75,"passed_time":0.1588124169,"remaining_time":1.930824648},
{"learn":[0.3524409864],"iteration":76,"passed_time":0.1599059178,"remaining_time":1.916794313},
{"learn":[0.3519916751],"iteration":77,"passed_time":0.1611610456,"remaining_time":1.905006206},
{"learn":[0.3515595055],"iteration":78,"passed_time":0.1624216669,"remaining_time":1.8935488},
{"learn":[0.3513176705],"iteration":79,"passed_time":0.1635883978,"remaining_time":1.881266574},
{"learn":[0.3510144034],"iteration":80,"passed_time":0.1648849739,"remaining_time":1.870731988},
{"learn":[0.3507236669],"iteration":81,"passed_time":0.1661738596,"remaining_time":1.860336623},
{"learn":[0.3505780764],"iteration":82,"passed_time":0.1671989564,"remaining_time":1.847246302},
{"learn":[0.3503060846],"iteration":83,"passed_time":0.1684637309,"remaining_time":1.837056875},
{"learn":[0.3502081136],"iteration":84,"passed_time":0.1695375733,"remaining_time":1.825022113},
{"learn":[0.3500302499],"iteration":85,"passed_time":0.1705906691,"remaining_time":1.813021763},
{"learn":[0.3498425946],"iteration":86,"passed_time":0.1717371805,"remaining_time":1.8022534},
{"learn":[0.3496504474],"iteration":87,"passed_time":0.1728257291,"remaining_time":1.791103011},
{"learn":[0.3494762531],"iteration":88,"passed_time":0.1738034117,"remaining_time":1.77904391},
{"learn":[0.3492510093],"iteration":89,"passed_time":0.1750139862,"remaining_time":1.769585861},
{"learn":[0.3489491387],"iteration":90,"passed_time":0.1763731359,"remaining_time":1.761793192},
{"learn":[0.3487339791],"iteration":91,"passed_time":0.1775404974,"remaining_time":1.752247517},
{"learn":[0.3485252705],"iteration":92,"passed_time":0.1786219769,"remaining_time":1.742044442},
{"learn":[0.348456806],"iteration":93,"passed_time":0.1795028164,"remaining_time":1.730101614},
{"learn":[0.3483263529],"iteration":94,"passed_time":0.1805168919,"remaining_time":1.719660918},
{"learn":[0.3480641249],"iteration":95,"passed_time":0.1819537217,"remaining_time":1.713397546},
{"learn":[0.3478131417],"iteration":96,"passed_time":0.1833315091,"remaining_time":1.706684049},
{"learn":[0.3475786019],"iteration":97,"passed_time":0.184579561,"remaining_time":1.698885347},
{"learn":[0.3474183265],"iteration":98,"passed_time":0.1858171599,"remaining_time":1.691123849},
{"learn":[0.3472660475],"iteration":99,"passed_time":0.1871707636,"remaining_time":1.684536873},
{"learn":[0.3470547142],"iteration":100,"passed_time":0.1883424333,"remaining_time":1.676434134},
{"learn":[0.3469081456],"iteration":101,"passed_time":0.1894304841,"remaining_time":1.667731125},
{"learn":[0.3468416149],"iteration":102,"passed_time":0.1905468112,"remaining_time":1.65942223},
{"learn":[0.3467047446],"iteration":103,"passed_time":0.1917154028,"remaining_time":1.651701932},
{"learn":[0.3465145527],"iteration":104,"passed_time":0.1930776232,"remaining_time":1.645756884},
{"learn":[0.3463309979],"iteration":105,"passed_time":0.1944942592,"remaining_time":1.640357242},
{"learn":[0.3462575511],"iteration":106,"passed_time":0.195771519,"remaining_time":1.633868846},
{"learn":[0.3461829634],"iteration":107,"passed_time":0.196858301,"remaining_time":1.625903745},
{"learn":[0.3460688816],"iteration":108,"passed_time":0.198093793,"remaining_time":1.619280455},
{"learn":[0.3459072731],"iteration":109,"passed_time":0.1995194262,"remaining_time":1.614293539},
{"learn":[0.3458447998],"iteration":110,"passed_time":0.2007860564,"remaining_time":1.608097335},
{"learn":[0.3458161464],"iteration":111,"passed_time":0.2017469684,"remaining_time":1.599565249},
{"learn":[0.3456683852],"iteration":112,"passed_time":0.2030502519,"remaining_time":1.593854632},
{"learn":[0.3455979756],"iteration":113,"passed_time":0.2041388868,"remaining_time":1.586553103},
{"learn":[0.3454602408],"iteration":114,"passed_time":0.2055425982,"remaining_time":1.581784343},
{"learn":[0.3453284751],"iteration":115,"passed_time":0.2068349206,"remaining_time":1.57622474},
{"learn":[0.345203871],"iteration":116,"passed_time":0.2081642125,"remaining_time":1.571017091},
{"learn":[0.3450822783],"iteration":117,"passed_time":0.2094562768,"remaining_time":1.565596916},
{"learn":[0.345006609],"iteration":118,"passed_time":0.2107611632,"remaining_time":1.560341049},
{"learn":[0.3449592828],"iteration":119,"passed_time":0.2118363577,"remaining_time":1.553466623},
{"learn":[0.3448521123],"iteration":120,"passed_time":0.2132930926,"remaining_time":1.549459739},
{"learn":[0.3447831135],"iteration":121,"passed_time":0.2145193185,"remaining_time":1.543835751},
{"learn":[0.3447653295],"iteration":122,"passed_time":0.2156068388,"remaining_time":1.53729429},
{"learn":[0.3447451235],"iteration":123,"passed_time":0.2165716198,"remaining_time":1.529973701},
{"learn":[0.3446957489],"iteration":124,"passed_time":0.2176398856,"remaining_time":1.523479199},
{"learn":[0.3446314009],"iteration":125,"passed_time":0.2188026182,"remaining_time":1.517726098},
{"learn":[0.3445375607],"iteration":126,"passed_time":0.2200600931,"remaining_time":1.512696545},
{"learn":[0.3445070799],"iteration":127,"passed_time":0.2212610881,"remaining_time":1.507341163},
{"learn":[0.3444666323],"iteration":128,"passed_time":0.2223445576,"remaining_time":1.501256664},
{"learn":[0.3444406655],"iteration":129,"passed_time":0.2234922714,"remaining_time":1.495679047},
{"learn":[0.3444273034],"iteration":130,"passed_time":0.2244959865,"remaining_time":1.489213834},
{"learn":[0.3444131052],"iteration":131,"passed_time":0.2254124817,"remaining_time":1.482257834},
{"learn":[0.3443877411],"iteration":132,"passed_time":0.2265139216,"remaining_time":1.476598271},
{"learn":[0.3443353096],"iteration":133,"passed_time":0.227855283,"remaining_time":1.472557277},
{"learn":[0.3442517006],"iteration":134,"passed_time":0.2292557579,"remaining_time":1.468935041},
{"learn":[0.3442389915],"iteration":135,"passed_time":0.230227606,"remaining_time":1.462622438},
{"learn":[0.3442272076],"iteration":136,"passed_time":0.2312159022,"remaining_time":1.456491413},
{"learn":[0.3441701192],"iteration":137,"passed_time":0.2324465525,"remaining_time":1.451948755},
{"learn":[0.3441198394],"iteration":138,"passed_time":0.233890347,"remaining_time":1.44877402},
{"learn":[0.34408959],"iteration":139,"passed_time":0.2349263785,"remaining_time":1.443119182},
{"learn":[0.3440555978],"iteration":140,"passed_time":0.2359281692,"remaining_time":1.437321258},
{"learn":[0.3440144003],"iteration":141,"passed_time":0.2370510748,"remaining_time":1.432322691},
{"learn":[0.3439399707],"iteration":142,"passed_time":0.2383463396,"remaining_time":1.42841128},
{"learn":[0.3439089653],"iteration":143,"passed_time":0.2393852328,"remaining_time":1.423012217},
{"learn":[0.3438841891],"iteration":144,"passed_time":0.2404581608,"remaining_time":1.417873983},
{"learn":[0.3438442583],"iteration":145,"passed_time":0.2415415808,"remaining_time":1.412852808},
{"learn":[0.3438240882],"iteration":146,"passed_time":0.2425305604,"remaining_time":1.407337198},
{"learn":[0.3437618855],"iteration":147,"passed_time":0.2438192651,"remaining_time":1.403608202},
{"learn":[0.343737394],"iteration":148,"passed_time":0.2450384227,"remaining_time":1.39951475},
{"learn":[0.343702506],"iteration":149,"passed_time":0.2461781507,"remaining_time":1.395009521},
{"learn":[0.343696698],"iteration":150,"passed_time":0.2471402716,"remaining_time":1.389550269},
{"learn":[0.3436393471],"iteration":151,"passed_time":0.2484976001,"remaining_time":1.386355032},
{"learn":[0.3436236712],"iteration":152,"passed_time":0.2495817309,"remaining_time":1.381671412},
{"learn":[0.3436207024],"iteration":153,"passed_time":0.2504422461,"remaining_time":1.375806105},
{"learn":[0.3435854377],"iteration":154,"passed_time":0.2516470227,"remaining_time":1.371882156},
{"learn":[0.3435679019],"iteration":155,"passed_time":0.2526500335,"remaining_time":1.366901463},
{"learn":[0.3435390136],"iteration":156,"passed_time":0.2542078149,"remaining_time":1.364950242},
{"learn":[0.3435355055],"iteration":157,"passed_time":0.255231448,"remaining_time":1.360157463},
{"learn":[0.3434852715],"iteration":158,"passed_time":0.2566127155,"remaining_time":1.357303734},
{"learn":[0.3434677517],"iteration":159,"passed_time":0.2578593156,"remaining_time":1.353761407},
{"learn":[0.3434226734],"iteration":160,"passed_time":0.2593257968,"remaining_time":1.351393438},
{"learn":[0.3434154249],"iteration":161,"passed_time":0.2603423865,"remaining_time":1.346709382},
{"learn":[0.3433946299],"iteration":162,"passed_time":0.2617856165,"remaining_time":1.34426111},
{"learn":[0.3433522758],"iteration":163,"passed_time":0.2631819292,"remaining_time":1.341585932},
{"learn":[0.3433289541],"iteration":164,"passed_time":0.2642905322,"remaining_time":1.337470269},
{"learn":[0.3433002594],"iteration":165,"passed_time":0.2654127919,"remaining_time":1.333459448},
{"learn":[0.3432662129],"iteration":166,"passed_time":0.2666980207,"remaining_time":1.330296115},
{"learn":[0.3432273965],"iteration":167,"passed_time":0.26814764,"remaining_time":1.327969265},
{"learn":[0.3431942842],"iteration":168,"passed_time":0.2694775989,"remaining_time":1.325064407},
{"learn":[0.3431823048],"iteration":169,"passed_time":0.2705426228,"remaining_time":1.32088457},
{"learn":[0.343179729],"iteration":170,"passed_time":0.271500248,"remaining_time":1.316220501},
{"learn":[0.3431432563],"iteration":171,"passed_time":0.272939441,"remaining_time":1.313917774},
{"learn":[0.3431265577],"iteration":172,"passed_time":0.2739287279,"remaining_time":1.309474323},
{"learn":[0.343117749],"iteration":173,"passed_time":0.275016929,"remaining_time":1.305540134},
{"learn":[0.3431076272],"iteration":174,"passed_time":0.2762231271,"remaining_time":1.302194742},
{"learn":[0.3431059289],"iteration":175,"passed_time":0.2771345865,"remaining_time":1.297493746},
{"learn":[0.3430902534],"iteration":176,"passed_time":0.2784356926,"remaining_time":1.294647316},
{"learn":[0.343081996],"iteration":177,"passed_time":0.2797128232,"remaining_time":1.291707532},
{"learn":[0.3430792424],"iteration":178,"passed_time":0.2806703732,"remaining_time":1.287320539},
{"learn":[0.3430637604],"iteration":179,"passed_time":0.2819546151,"remaining_time":1.284459913},
{"learn":[0.3430552002],"iteration":180,"passed_time":0.2831184862,"remaining_time":1.281072045},
{"learn":[0.3430374894],"iteration":181,"passed_time":0.2843216096,"remaining_time":1.277885037},
{"learn":[0.3430235364],"iteration":182,"passed_time":0.2854182484,"remaining_time":1.274244311},
{"learn":[0.3430120186],"iteration":183,"passed_time":0.2867536044,"remaining_time":1.271689898},
{"learn":[0.3429994027],"iteration":184,"passed_time":0.2880591951,"remaining_time":1.269017535},
{"learn":[0.3429848661],"iteration":185,"passed_time":0.2890412372,"remaining_time":1.264943909},
{"learn":[0.3429835973],"iteration":186,"passed_time":0.289952002,"remaining_time":1.260593463},
{"learn":[0.3429694814],"iteration":187,"passed_time":0.2911513961,"remaining_time":1.257526243},
{"learn":[0.342946696],"iteration":188,"passed_time":0.292432777,"remaining_time":1.254830593},
{"learn":[0.342940141],"iteration":189,"passed_time":0.2934537934,"remaining_time":1.251039856},
{"learn":[0.3429151401],"iteration":190,"passed_time":0.2947187344,"remaining_time":1.248311288},
{"learn":[0.3429060711],"iteration":191,"passed_time":0.2959258538,"remaining_time":1.245354635},
{"learn":[0.3428933674],"iteration":192,"passed_time":0.2973198587,"remaining_time":1.243197544},
{"learn":[0.3428812706],"iteration":193,"passed_time":0.2984866179,"remaining_time":1.240104196},
{"learn":[0.3428698895],"iteration":194,"passed_time":0.2997699692,"remaining_time":1.237511924},
{"learn":[0.3428646743],"iteration":195,"passed_time":0.3008749428,"remaining_time":1.234201296},
{"learn":[0.3428590107],"iteration":196,"passed_time":0.3019557366,"remaining_time":1.2308145},
{"learn":[0.342846772],"iteration":197,"passed_time":0.3031392833,"remaining_time":1.227867198},
{"learn":[0.3428353935],"iteration":198,"passed_time":0.3042742881,"remaining_time":1.224742235},
{"learn":[0.3428284558],"iteration":199,"passed_time":0.3054106522,"remaining_time":1.221642609},
{"learn":[0.3428188426],"iteration":200,"passed_time":0.3067151801,"remaining_time":1.219230989},
{"learn":[0.3428119424],"iteration":201,"passed_time":0.307750202,"remaining_time":1.215765649},
{"learn":[0.3428129417],"iteration":202,"passed_time":0.3087998672,"remaining_time":1.212381745},
{"learn":[0.342796657],"iteration":203,"passed_time":0.3103568024,"remaining_time":1.211000072},
{"learn":[0.3427895324],"iteration":204,"passed_time":0.311475775,"remaining_time":1.207918249},
{"learn":[0.3427716772],"iteration":205,"passed_time":0.3127389611,"remaining_time":1.205411336},
{"learn":[0.3427556349],"iteration":206,"passed_time":0.3142033094,"remaining_time":1.203687074},
{"learn":[0.3427496423],"iteration":207,"passed_time":0.3155321103,"remaining_time":1.201449189},
{"learn":[0.3427465584],"iteration":208,"passed_time":0.3167645886,"remaining_time":1.198855453},
{"learn":[0.342739612],"iteration":209,"passed_time":0.318064213,"remaining_time":1.196527277},
{"learn":[0.3427392562],"iteration":210,"passed_time":0.3191448407,"remaining_time":1.193389949},
{"learn":[0.3427371142],"iteration":211,"passed_time":0.3201753841,"remaining_time":1.190085862},
{"learn":[0.342736831],"iteration":212,"passed_time":0.3212536471,"remaining_time":1.186979438},
{"learn":[0.3427222952],"iteration":213,"passed_time":0.3226650934,"remaining_time":1.185115717},
{"learn":[0.3427211533],"iteration":214,"passed_time":0.3236746543,"remaining_time":1.181788854},
{"learn":[0.3427207499],"iteration":215,"passed_time":0.324716048,"remaining_time":1.178598989},
{"learn":[0.3427070967],"iteration":216,"passed_time":0.3260999034,"remaining_time":1.176664628},
{"learn":[0.3426992788],"iteration":217,"passed_time":0.3274317939,"remaining_time":1.174548912},
{"learn":[0.342699733],"iteration":218,"passed_time":0.3284905281,"remaining_time":1.171466221},
{"learn":[0.3426987631],"iteration":219,"passed_time":0.3295226587,"remaining_time":1.168307608},
{"learn":[0.3426916132],"iteration":220,"passed_time":0.3306823075,"remaining_time":1.165617726},
{"learn":[0.3426915424],"iteration":221,"passed_time":0.3316212009,"remaining_time":1.162167992},
{"learn":[0.3426910726],"iteration":222,"passed_time":0.3325577831,"remaining_time":1.158732724},
{"learn":[0.3426909999],"iteration":223,"passed_time":0.3335095858,"remaining_time":1.155372494},
{"learn":[0.3426845308],"iteration":224,"passed_time":0.3347269931,"remaining_time":1.152948532},
{"learn":[0.3426829347],"iteration":225,"passed_time":0.3356583561,"remaining_time":1.149555609},
{"learn":[0.3426795949],"iteration":226,"passed_time":0.3367680771,"remaining_time":1.146791734},
{"learn":[0.3426774861],"iteration":227,"passed_time":0.3380340583,"remaining_time":1.14457146},
{"learn":[0.3426655566],"iteration":228,"passed_time":0.3392948717,"remaining_time":1.142342123},
{"learn":[0.3426624821],"iteration":229,"passed_time":0.3400735612,"remaining_time":1.13850714},
{"learn":[0.3426531547],"iteration":230,"passed_time":0.3415119874,"remaining_time":1.136894884},
{"learn":[0.3426478203],"iteration":231,"passed_time":0.3427235028,"remaining_time":1.134532975},
{"learn":[0.3426467263],"iteration":232,"passed_time":0.3437926796,"remaining_time":1.131712383},
{"learn":[0.3426425499],"iteration":233,"passed_time":0.3450286676,"remaining_time":1.129452818},
{"learn":[0.3426413812],"iteration":234,"passed_time":0.3460167838,"remaining_time":1.126395062},
{"learn":[0.3426373524],"iteration":235,"passed_time":0.347266691,"remaining_time":1.124202339},
{"learn":[0.3426342516],"iteration":236,"passed_time":0.348434143,"remaining_time":1.121752114},
{"learn":[0.3426274304],"iteration":237,"passed_time":0.3496821829,"remaining_time":1.119570687},
{"learn":[0.3426214068],"iteration":238,"passed_time":0.3508384928,"remaining_time":1.117104992},
{"learn":[0.3426224384],"iteration":239,"passed_time":0.3517577328,"remaining_time":1.113899487},
{"learn":[0.3426175597],"iteration":240,"passed_time":0.3529209326,"remaining_time":1.111481277},
{"learn":[0.3426144387],"iteration":241,"passed_time":0.3541422681,"remaining_time":1.109255534},
{"learn":[0.3426148224],"iteration":242,"passed_time":0.3552729355,"remaining_time":1.106755606},
{"learn":[0.3426099915],"iteration":243,"passed_time":0.3564124928,"remaining_time":1.104294445},
{"learn":[0.3426086852],"iteration":244,"passed_time":0.357526603,"remaining_time":1.101765654},
{"learn":[0.3425994827],"iteration":245,"passed_time":0.3590028029,"remaining_time":1.100358185},
{"learn":[0.3425994196],"iteration":246,"passed_time":0.359892186,"remaining_time":1.097161198},
{"learn":[0.342590601],"iteration":247,"passed_time":0.3613079101,"remaining_time":1.095578824},
{"learn":[0.3425861235],"iteration":248,"passed_time":0.3624503672,"remaining_time":1.093173597},
{"learn":[0.3425812417],"iteration":249,"passed_time":0.3635511638,"remaining_time":1.090653491},
{"learn":[0.3425812417],"iteration":250,"passed_time":0.3645230323,"remaining_time":1.087759965},
{"learn":[0.3425799387],"iteration":251,"passed_time":0.3656894548,"remaining_time":1.085459175},
{"learn":[0.3425814045],"iteration":252,"passed_time":0.3667158607,"remaining_time":1.082753944},
{"learn":[0.3425759517],"iteration":253,"passed_time":0.367970498,"remaining_time":1.08073225},
{"learn":[0.3425740056],"iteration":254,"passed_time":0.3691046681,"remaining_time":1.078364619},
{"learn":[0.3425676988],"iteration":255,"passed_time":0.3701101169,"remaining_time":1.075632527},
{"learn":[0.3425667293],"iteration":256,"passed_time":0.3712900592,"remaining_time":1.073418342},
{"learn":[0.3425643292],"iteration":257,"passed_time":0.3723118965,"remaining_time":1.07075747},
{"learn":[0.3425617867],"iteration":258,"passed_time":0.3734655421,"remaining_time":1.068486358},
{"learn":[0.3425618287],"iteration":259,"passed_time":0.3744540323,"remaining_time":1.065753784},
{"learn":[0.3425580232],"iteration":260,"passed_time":0.3754691849,"remaining_time":1.063110067},
{"learn":[0.3425591203],"iteration":261,"passed_time":0.376221578,"remaining_time":1.059738643},
{"learn":[0.3425569398],"iteration":262,"passed_time":0.3773563357,"remaining_time":1.057458629},
{"learn":[0.3425535391],"iteration":263,"passed_time":0.3786395934,"remaining_time":1.055601291},
{"learn":[0.3425511453],"iteration":264,"passed_time":0.3796290517,"remaining_time":1.052933408},
{"learn":[0.342549323],"iteration":265,"passed_time":0.3808649738,"remaining_time":1.050958236},
{"learn":[0.3425476883],"iteration":266,"passed_time":0.382149781,"remaining_time":1.049122807},
{"learn":[0.3425449562],"iteration":267,"passed_time":0.3832622495,"remaining_time":1.046820771},
{"learn":[0.3425408455],"iteration":268,"passed_time":0.3845340351,"remaining_time":1.044960519},
{"learn":[0.3425407739],"iteration":269,"passed_time":0.3854688502,"remaining_time":1.042193558},
{"learn":[0.3425384066],"iteration":270,"passed_time":0.3864920644,"remaining_time":1.039677915},
{"learn":[0.3425386451],"iteration":271,"passed_time":0.3873417689,"remaining_time":1.036708852},
{"learn":[0.342530791],"iteration":272,"passed_time":0.3886789844,"remaining_time":1.035053559},
{"learn":[0.3425314736],"iteration":273,"passed_time":0.3896662185,"remaining_time":1.032473265},
{"learn":[0.3425291303],"iteration":274,"passed_time":0.3907479842,"remaining_time":1.030153777},
{"learn":[0.3425293222],"iteration":275,"passed_time":0.3915710267,"remaining_time":1.027164577},
{"learn":[0.3425261443],"iteration":276,"passed_time":0.3926713784,"remaining_time":1.024914825},
{"learn":[0.342525564],"iteration":277,"passed_time":0.3936643333,"remaining_time":1.02239442},
{"learn":[0.3425225474],"iteration":278,"passed_time":0.3946916464,"remaining_time":1.019973753},
{"learn":[0.3425230721],"iteration":279,"passed_time":0.3955002581,"remaining_time":1.017000664},
{"learn":[0.3425200396],"iteration":280,"passed_time":0.3968540915,"remaining_time":1.015438049},
{"learn":[0.3425162597],"iteration":281,"passed_time":0.3981053577,"remaining_time":1.013615769},
{"learn":[0.3425101266],"iteration":282,"passed_time":0.3994253888,"remaining_time":1.011971745},
{"learn":[0.3425101678],"iteration":283,"passed_time":0.4004267545,"remaining_time":1.009526606},
{"learn":[0.3425061349],"iteration":284,"passed_time":0.4015808818,"remaining_time":1.007474844},
{"learn":[0.3425045266],"iteration":285,"passed_time":0.4028604477,"remaining_time":1.005742516},
{"learn":[0.3425029649],"iteration":286,"passed_time":0.4037459153,"remaining_time":1.003034277},
{"learn":[0.3425027186],"iteration":287,"passed_time":0.4047914165,"remaining_time":1.000734335},
{"learn":[0.3424990593],"iteration":288,"passed_time":0.405974032,"remaining_time":0.9987804039},
{"learn":[0.3424989311],"iteration":289,"passed_time":0.4070688124,"remaining_time":0.9966167476},
{"learn":[0.3424934923],"iteration":290,"passed_time":0.4082878994,"remaining_time":0.9947633013},
{"learn":[0.3424918417],"iteration":291,"passed_time":0.4095143217,"remaining_time":0.9929319855},
{"learn":[0.3424925957],"iteration":292,"passed_time":0.4105322923,"remaining_time":0.990601811},
{"learn":[0.3424870856],"iteration":293,"passed_time":0.4116448869,"remaining_time":0.9885077897},
{"learn":[0.3424860595],"iteration":294,"passed_time":0.4129954724,"remaining_time":0.9869891797},
{"learn":[0.3424869579],"iteration":295,"passed_time":0.4139507617,"remaining_time":0.9845315412},
{"learn":[0.3424835489],"iteration":296,"passed_time":0.4151918023,"remaining_time":0.9827603941},
{"learn":[0.3424836628],"iteration":297,"passed_time":0.4160536946,"remaining_time":0.9800996429},
{"learn":[0.3424833503],"iteration":298,"passed_time":0.4170483935,"remaining_time":0.9777622872},
{"learn":[0.34247839],"iteration":299,"passed_time":0.4184242673,"remaining_time":0.9763232904},
{"learn":[0.3424719998],"iteration":300,"passed_time":0.4199681184,"remaining_time":0.9752747999},
{"learn":[0.3424708056],"iteration":301,"passed_time":0.4210046888,"remaining_time":0.973050572},
{"learn":[0.3424715675],"iteration":302,"passed_time":0.4221106044,"remaining_time":0.9709937006},
{"learn":[0.3424692332],"iteration":303,"passed_time":0.4236359359,"remaining_time":0.9699033269},
{"learn":[0.3424667081],"iteration":304,"passed_time":0.4246264206,"remaining_time":0.967591352},
{"learn":[0.3424659915],"iteration":305,"passed_time":0.425478779,"remaining_time":0.9649747471},
{"learn":[0.3424659176],"iteration":306,"passed_time":0.4267598856,"remaining_time":0.9633374617},
{"learn":[0.3424610076],"iteration":307,"passed_time":0.4277225808,"remaining_time":0.9609870971},
{"learn":[0.3424577682],"iteration":308,"passed_time":0.4290663261,"remaining_time":0.959497836},
{"learn":[0.3424578159],"iteration":309,"passed_time":0.4299957916,"remaining_time":0.957087407},
{"learn":[0.3424556012],"iteration":310,"passed_time":0.4312653157,"remaining_time":0.9554398795},
{"learn":[0.3424556012],"iteration":311,"passed_time":0.4322966765,"remaining_time":0.9532695943},
{"learn":[0.3424556197],"iteration":312,"passed_time":0.4334895331,"remaining_time":0.9514610519},
{"learn":[0.3424566152],"iteration":313,"passed_time":0.4346799,"remaining_time":0.9496509917},
{"learn":[0.3424530789],"iteration":314,"passed_time":0.4359679453,"remaining_time":0.9480572779},
{"learn":[0.3424530789],"iteration":315,"passed_time":0.4369636818,"remaining_time":0.9458327796},
{"learn":[0.3424533173],"iteration":316,"passed_time":0.4379895776,"remaining_time":0.9436810141},
{"learn":[0.3424533173],"iteration":317,"passed_time":0.4388173771,"remaining_time":0.9411114817},
{"learn":[0.3424549438],"iteration":318,"passed_time":0.4399958984,"remaining_time":0.9393015887},
{"learn":[0.3424528517],"iteration":319,"passed_time":0.4411747215,"remaining_time":0.9374962832},
{"learn":[0.3424469652],"iteration":320,"passed_time":0.4426576001,"remaining_time":0.9363380388},
{"learn":[0.3424470794],"iteration":321,"passed_time":0.4436838652,"remaining_time":0.9342163373},
{"learn":[0.3424441765],"iteration":322,"passed_time":0.4451004498,"remaining_time":0.9329195185},
{"learn":[0.3424428647],"iteration":323,"passed_time":0.4461656025,"remaining_time":0.9308887263},
{"learn":[0.3424430541],"iteration":324,"passed_time":0.4472159413,"remaining_time":0.9288331089},
{"learn":[0.3424428873],"iteration":325,"passed_time":0.4482430649,"remaining_time":0.9267356617},
{"learn":[0.3424430288],"iteration":326,"passed_time":0.449146476,"remaining_time":0.9243901478},
{"learn":[0.3424422606],"iteration":327,"passed_time":0.4501926822,"remaining_time":0.9223459831},
{"learn":[0.3424430188],"iteration":328,"passed_time":0.451685927,"remaining_time":0.9212196262},
{"learn":[0.3424426371],"iteration":329,"passed_time":0.4525858231,"remaining_time":0.9188863682},
{"learn":[0.3424391391],"iteration":330,"passed_time":0.4538716158,"remaining_time":0.9173417249},
{"learn":[0.3424365367],"iteration":331,"passed_time":0.4549937608,"remaining_time":0.9154693742},
{"learn":[0.3424366062],"iteration":332,"passed_time":0.4561232123,"remaining_time":0.9136161641},
{"learn":[0.3424351237],"iteration":333,"passed_time":0.4570949347,"remaining_time":0.9114527739},
{"learn":[0.3424346405],"iteration":334,"passed_time":0.4584053544,"remaining_time":0.9099688379},
{"learn":[0.3424332903],"iteration":335,"passed_time":0.4598486059,"remaining_time":0.9087484354},
{"learn":[0.342432217],"iteration":336,"passed_time":0.461068218,"remaining_time":0.9070867315},
{"learn":[0.3424314144],"iteration":337,"passed_time":0.4624550003,"remaining_time":0.9057550598},
{"learn":[0.3424309812],"iteration":338,"passed_time":0.4637245882,"remaining_time":0.904194551},
{"learn":[0.3424312912],"iteration":339,"passed_time":0.4647614926,"remaining_time":0.9021840739},
{"learn":[0.3424303559],"iteration":340,"passed_time":0.4659859238,"remaining_time":0.900541712},
{"learn":[0.3424305945],"iteration":341,"passed_time":0.4670081155,"remaining_time":0.8985126901},
{"learn":[0.3424257372],"iteration":342,"passed_time":0.4683887401,"remaining_time":0.8971760999},
{"learn":[0.3424266435],"iteration":343,"passed_time":0.469280917,"remaining_time":0.8949077953},
{"learn":[0.3424245904],"iteration":344,"passed_time":0.4705183472,"remaining_time":0.8933029491},
{"learn":[0.342423993],"iteration":345,"passed_time":0.4715024951,"remaining_time":0.8912214792},
{"learn":[0.3424215936],"iteration":346,"passed_time":0.4728793731,"remaining_time":0.8898853909},
{"learn":[0.3424216375],"iteration":347,"passed_time":0.4745812253,"remaining_time":0.8891579279},
{"learn":[0.3424207646],"iteration":348,"passed_time":0.4760911901,"remaining_time":0.8880669476},
{"learn":[0.3424177239],"iteration":349,"passed_time":0.4772533059,"remaining_time":0.8863275681},
{"learn":[0.3424171992],"iteration":350,"passed_time":0.4781703811,"remaining_time":0.884138397},
{"learn":[0.3424180817],"iteration":351,"passed_time":0.4791996645,"remaining_time":0.8821630188},
{"learn":[0.3424181771],"iteration":352,"passed_time":0.4801058507,"remaining_time":0.8799673808},
{"learn":[0.3424183538],"iteration":353,"passed_time":0.4811856012,"remaining_time":0.8780957581},
{"learn":[0.3424184015],"iteration":354,"passed_time":0.4820951485,"remaining_time":0.8759193544},
{"learn":[0.3424194244],"iteration":355,"passed_time":0.4830671428,"remaining_time":0.8738630336},
{"learn":[0.3424181087],"iteration":356,"passed_time":0.4841134185,"remaining_time":0.8719465773},
{"learn":[0.3424114879],"iteration":357,"passed_time":0.4853683361,"remaining_time":0.8704091391},
{"learn":[0.3424114879],"iteration":358,"passed_time":0.4861833718,"remaining_time":0.8680878588},
{"learn":[0.3424155411],"iteration":359,"passed_time":0.4870964967,"remaining_time":0.8659493274},
{"learn":[0.3424130831],"iteration":360,"passed_time":0.4880938721,"remaining_time":0.8639667155},
{"learn":[0.3424125095],"iteration":361,"passed_time":0.4892733719,"remaining_time":0.8623105283},
{"learn":[0.3424128673],"iteration":362,"passed_time":0.4903893216,"remaining_time":0.8605454486},
{"learn":[0.3424080125],"iteration":363,"passed_time":0.4918072421,"remaining_time":0.8593115548},
{"learn":[0.3424080125],"iteration":364,"passed_time":0.4931649886,"remaining_time":0.8579719665},
{"learn":[0.3424082987],"iteration":365,"passed_time":0.4940861703,"remaining_time":0.8558760436},
{"learn":[0.3424082987],"iteration":366,"passed_time":0.4950206067,"remaining_time":0.8538093843},
{"learn":[0.3424103223],"iteration":367,"passed_time":0.4961999941,"remaining_time":0.8521695551},
{"learn":[0.3424103949],"iteration":368,"passed_time":0.4971203883,"remaining_time":0.850089336},
{"learn":[0.3424091988],"iteration":369,"passed_time":0.4981486771,"remaining_time":0.8481990988},
{"learn":[0.3424085033],"iteration":370,"passed_time":0.4992529331,"remaining_time":0.8464423043},
{"learn":[0.3424097196],"iteration":371,"passed_time":0.5001577269,"remaining_time":0.8443522917},
{"learn":[0.3424109058],"iteration":372,"passed_time":0.5011776751,"remaining_time":0.8424622046},
{"learn":[0.3424099041],"iteration":373,"passed_time":0.5021549503,"remaining_time":0.8405053447},
{"learn":[0.3424096325],"iteration":374,"passed_time":0.503275835,"remaining_time":0.8387930583},
{"learn":[0.3424087474],"iteration":375,"passed_time":0.5045299909,"remaining_time":0.8373050912},
{"learn":[0.3424070284],"iteration":376,"passed_time":0.5058938085,"remaining_time":0.8359995827},
{"learn":[0.3424062148],"iteration":377,"passed_time":0.5071784638,"remaining_time":0.834563504},
{"learn":[0.3424027923],"iteration":378,"passed_time":0.5085501871,"remaining_time":0.8332708871},
{"learn":[0.3424039348],"iteration":379,"passed_time":0.5095036073,"remaining_time":0.8312953593},
{"learn":[0.342402023],"iteration":380,"passed_time":0.5107568557,"remaining_time":0.8298123193},
{"learn":[0.3424024019],"iteration":381,"passed_time":0.5119485716,"remaining_time":0.8282309351},
{"learn":[0.3424034978],"iteration":382,"passed_time":0.512915395,"remaining_time":0.8262892917},
{"learn":[0.3424029493],"iteration":383,"passed_time":0.5139911522,"remaining_time":0.8245274733},
{"learn":[0.3424037749],"iteration":384,"passed_time":0.515059925,"remaining_time":0.8227580621},
{"learn":[0.342401746],"iteration":385,"passed_time":0.5164304397,"remaining_time":0.8214722538},
{"learn":[0.3424021524],"iteration":386,"passed_time":0.5176728543,"remaining_time":0.8199831},
{"learn":[0.3423972036],"iteration":387,"passed_time":0.5190020706,"remaining_time":0.818632132},
{"learn":[0.342396154],"iteration":388,"passed_time":0.5199082579,"remaining_time":0.8166168267},
{"learn":[0.3423962971],"iteration":389,"passed_time":0.5210377494,"remaining_time":0.8149564798},
{"learn":[0.3423969639],"iteration":390,"passed_time":0.5221220132,"remaining_time":0.8132284043},
{"learn":[0.3423963639],"iteration":391,"passed_time":0.5234169013,"remaining_time":0.8118302959},
{"learn":[0.3423964779],"iteration":392,"passed_time":0.5245023661,"remaining_time":0.8101092525},
{"learn":[0.3423964779],"iteration":393,"passed_time":0.5256143981,"remaining_time":0.8084322976},
{"learn":[0.3423972888],"iteration":394,"passed_time":0.5269029858,"remaining_time":0.8070286238},
{"learn":[0.342397241],"iteration":395,"passed_time":0.5281381959,"remaining_time":0.805544117},
{"learn":[0.3423958074],"iteration":396,"passed_time":0.5294218456,"remaining_time":0.8041344405},
{"learn":[0.3423954247],"iteration":397,"passed_time":0.530428483,"remaining_time":0.8023063989},
{"learn":[0.3423975221],"iteration":398,"passed_time":0.531629689,"remaining_time":0.8007755466},
{"learn":[0.3423956116],"iteration":399,"passed_time":0.5326290575,"remaining_time":0.7989435862},
{"learn":[0.3423932652],"iteration":400,"passed_time":0.5339341004,"remaining_time":0.7975723844},
{"learn":[0.3423932652],"iteration":401,"passed_time":0.5349721437,"remaining_time":0.7958043331},
{"learn":[0.3423932652],"iteration":402,"passed_time":0.535916402,"remaining_time":0.7939009727},
{"learn":[0.3423934031],"iteration":403,"passed_time":0.5369731755,"remaining_time":0.792168348},
{"learn":[0.3423931169],"iteration":404,"passed_time":0.537841988,"remaining_time":0.7901629206},
{"learn":[0.3423934746],"iteration":405,"passed_time":0.538746022,"remaining_time":0.7882146233},
{"learn":[0.3423911268],"iteration":406,"passed_time":0.5400234307,"remaining_time":0.7868154653},
{"learn":[0.3423911983],"iteration":407,"passed_time":0.541095987,"remaining_time":0.7851196674},
{"learn":[0.3423911983],"iteration":408,"passed_time":0.5420220012,"remaining_time":0.7832151655},
{"learn":[0.3423911983],"iteration":409,"passed_time":0.54299583,"remaining_time":0.7813842432},
{"learn":[0.3423911983],"iteration":410,"passed_time":0.5440658924,"remaining_time":0.779695403},
{"learn":[0.3423911983],"iteration":411,"passed_time":0.5451832253,"remaining_time":0.7780770302},
{"learn":[0.3423911983],"iteration":412,"passed_time":0.5461378007,"remaining_time":0.7762297555},
{"learn":[0.3423911983],"iteration":413,"passed_time":0.5470377862,"remaining_time":0.7743095235},
{"learn":[0.3423911983],"iteration":414,"passed_time":0.5481204253,"remaining_time":0.7726516839},
{"learn":[0.3423911983],"iteration":415,"passed_time":0.5490059186,"remaining_time":0.7707198473},
{"learn":[0.3423902827],"iteration":416,"passed_time":0.5505386893,"remaining_time":0.7696979757},
{"learn":[0.342390996],"iteration":417,"passed_time":0.5517188112,"remaining_time":0.768182651},
{"learn":[0.342390328],"iteration":418,"passed_time":0.552679707,"remaining_time":0.7663649398},
{"learn":[0.3423900404],"iteration":419,"passed_time":0.5540240711,"remaining_time":0.76508086},
{"learn":[0.3423891806],"iteration":420,"passed_time":0.555063662,"remaining_time":0.7633773404},
{"learn":[0.3423888467],"iteration":421,"passed_time":0.5559649708,"remaining_time":0.7614875666},
{"learn":[0.3423884411],"iteration":422,"passed_time":0.5571226772,"remaining_time":0.7599522098},
{"learn":[0.3423900618],"iteration":423,"passed_time":0.5582187475,"remaining_time":0.7583349023},
{"learn":[0.3423876966],"iteration":424,"passed_time":0.5591865663,"remaining_time":0.7565465309},
{"learn":[0.3423873841],"iteration":425,"passed_time":0.5602146365,"remaining_time":0.7548431957},
{"learn":[0.3423877869],"iteration":426,"passed_time":0.5614528358,"remaining_time":0.7534249997},
{"learn":[0.3423891464],"iteration":427,"passed_time":0.562481792,"remaining_time":0.7517280024},
{"learn":[0.3423875458],"iteration":428,"passed_time":0.5637335705,"remaining_time":0.7503306965},
{"learn":[0.3423869006],"iteration":429,"passed_time":0.5648363337,"remaining_time":0.7487365354},
{"learn":[0.3423868291],"iteration":430,"passed_time":0.5663238484,"remaining_time":0.747652598},
{"learn":[0.3423868291],"iteration":431,"passed_time":0.5672741395,"remaining_time":0.7458604427},
{"learn":[0.3423866281],"iteration":432,"passed_time":0.568560005,"remaining_time":0.7445116001},
{"learn":[0.3423866758],"iteration":433,"passed_time":0.5697017736,"remaining_time":0.742975124},
{"learn":[0.3423868677],"iteration":434,"passed_time":0.5705292597,"remaining_time":0.7410322569},
{"learn":[0.3423868677],"iteration":435,"passed_time":0.5714425062,"remaining_time":0.7392054437},
{"learn":[0.3423867383],"iteration":436,"passed_time":0.5727657523,"remaining_time":0.7379110264},
{"learn":[0.3423835092],"iteration":437,"passed_time":0.5739451366,"remaining_time":0.7364318876},
{"learn":[0.3423828414],"iteration":438,"passed_time":0.5750207841,"remaining_time":0.7348215487},
{"learn":[0.3423824746],"iteration":439,"passed_time":0.5761389642,"remaining_time":0.7332677726},
{"learn":[0.342379675],"iteration":440,"passed_time":0.5774031595,"remaining_time":0.731901057},
{"learn":[0.342379675],"iteration":441,"passed_time":0.5782281528,"remaining_time":0.7299803377},
{"learn":[0.342379675],"iteration":442,"passed_time":0.5792593775,"remaining_time":0.7283238674},
{"learn":[0.342379675],"iteration":443,"passed_time":0.5804898441,"remaining_time":0.7269197146},
{"learn":[0.342379675],"iteration":444,"passed_time":0.5814201507,"remaining_time":0.7251419857},
{"learn":[0.342379675],"iteration":445,"passed_time":0.5825022551,"remaining_time":0.7235566128},
{"learn":[0.342379675],"iteration":446,"passed_time":0.5834328689,"remaining_time":0.7217860772},
{"learn":[0.342379675],"iteration":447,"passed_time":0.5844602157,"remaining_time":0.7201384801},
{"learn":[0.342379675],"iteration":448,"passed_time":0.5855103777,"remaining_time":0.7185216439},
{"learn":[0.342379675],"iteration":449,"passed_time":0.5865741343,"remaining_time":0.7169239419},
{"learn":[0.342379675],"iteration":450,"passed_time":0.5877095878,"remaining_time":0.7154158841},
{"learn":[0.342379675],"iteration":451,"passed_time":0.5886979051,"remaining_time":0.7137310884},
{"learn":[0.342379675],"iteration":452,"passed_time":0.5896117226,"remaining_time":0.711959409},
{"learn":[0.342379675],"iteration":453,"passed_time":0.590993712,"remaining_time":0.7107545523},
{"learn":[0.342379675],"iteration":454,"passed_time":0.5921819589,"remaining_time":0.7093168519},
{"learn":[0.342379675],"iteration":455,"passed_time":0.5931439069,"remaining_time":0.7076102749},
{"learn":[0.342379675],"iteration":456,"passed_time":0.594148745,"remaining_time":0.705957918},
{"learn":[0.342379675],"iteration":457,"passed_time":0.5951293353,"remaining_time":0.7042796938},
{"learn":[0.342379675],"iteration":458,"passed_time":0.5963255888,"remaining_time":0.7028587005},
{"learn":[0.342379675],"iteration":459,"passed_time":0.5972416675,"remaining_time":0.7011097835},
{"learn":[0.3423797227],"iteration":460,"passed_time":0.5981511316,"remaining_time":0.699356746},
{"learn":[0.3423797227],"iteration":461,"passed_time":0.5992257174,"remaining_time":0.6977996449},
{"learn":[0.3423797227],"iteration":462,"passed_time":0.6001560332,"remaining_time":0.6960772998},
{"learn":[0.3423797227],"iteration":463,"passed_time":0.6012587649,"remaining_time":0.6945575387},
{"learn":[0.3423797227],"iteration":464,"passed_time":0.6023837989,"remaining_time":0.693065231},
{"learn":[0.3423797227],"iteration":465,"passed_time":0.6034888021,"remaining_time":0.6915515457},
{"learn":[0.3423796273],"iteration":466,"passed_time":0.6045398566,"remaining_time":0.6899780376},
{"learn":[0.3423796273],"iteration":467,"passed_time":0.6056706544,"remaining_time":0.6884974106},
{"learn":[0.3423796273],"iteration":468,"passed_time":0.6066870631,"remaining_time":0.6868887644},
{"learn":[0.3423796273],"iteration":469,"passed_time":0.6076473081,"remaining_time":0.6852193049},
{"learn":[0.3423796273],"iteration":470,"passed_time":0.6088512033,"remaining_time":0.6838265107},
{"learn":[0.3423796273],"iteration":471,"passed_time":0.6099163959,"remaining_time":0.6822793582},
{"learn":[0.3423796273],"iteration":472,"passed_time":0.6109528428,"remaining_time":0.680702216},
{"learn":[0.3423796273],"iteration":473,"passed_time":0.6120044489,"remaining_time":0.6791441774},
{"learn":[0.3423796273],"iteration":474,"passed_time":0.6131308841,"remaining_time":0.6776709771},
{"learn":[0.3423796273],"iteration":475,"passed_time":0.6141612637,"remaining_time":0.676093492},
{"learn":[0.3423796273],"iteration":476,"passed_time":0.6151457322,"remaining_time":0.6744679622},
{"learn":[0.3423796273],"iteration":477,"passed_time":0.6160795853,"remaining_time":0.67278984},
{"learn":[0.3423796273],"iteration":478,"passed_time":0.616956224,"remaining_time":0.6710525944},
{"learn":[0.3423796273],"iteration":479,"passed_time":0.6178768575,"remaining_time":0.6693665956},
{"learn":[0.3423796273],"iteration":480,"passed_time":0.6190329096,"remaining_time":0.6679377964},
{"learn":[0.3423796273],"iteration":481,"passed_time":0.6202111712,"remaining_time":0.6665339973},
{"learn":[0.3423796273],"iteration":482,"passed_time":0.620996962,"remaining_time":0.6647110339},
{"learn":[0.3423796273],"iteration":483,"passed_time":0.622011278,"remaining_time":0.6631359906},
{"learn":[0.3423796273],"iteration":484,"passed_time":0.6230648291,"remaining_time":0.6616049216},
{"learn":[0.3423796273],"iteration":485,"passed_time":0.6241127656,"remaining_time":0.6600698797},
{"learn":[0.3423796273],"iteration":486,"passed_time":0.6251852817,"remaining_time":0.65856273},
{"learn":[0.3423796273],"iteration":487,"passed_time":0.626100286,"remaining_time":0.6568921034},
{"learn":[0.3423796273],"iteration":488,"passed_time":0.6268892451,"remaining_time":0.6550928512},
{"learn":[0.3423796273],"iteration":489,"passed_time":0.6277103506,"remaining_time":0.6533311812},
{"learn":[0.3423796273],"iteration":490,"passed_time":0.6289581332,"remaining_time":0.6520156615},
{"learn":[0.3423796273],"iteration":491,"passed_time":0.6300088989,"remaining_time":0.6504969931},
{"learn":[0.3423796273],"iteration":492,"passed_time":0.6310207374,"remaining_time":0.6489401904},
{"learn":[0.3423796273],"iteration":493,"passed_time":0.6320729012,"remaining_time":0.6474268988},
{"learn":[0.3423796273],"iteration":494,"passed_time":0.6334260442,"remaining_time":0.6462225299},
{"learn":[0.3423796273],"iteration":495,"passed_time":0.634965864,"remaining_time":0.6452072489},
{"learn":[0.3423796273],"iteration":496,"passed_time":0.6359521545,"remaining_time":0.6436296453},
{"learn":[0.3423796273],"iteration":497,"passed_time":0.6369221646,"remaining_time":0.6420380053},
{"learn":[0.3423796273],"iteration":498,"passed_time":0.6380603277,"remaining_time":0.6406176837},
{"learn":[0.3423796273],"iteration":499,"passed_time":0.6391726619,"remaining_time":0.6391726619},
{"learn":[0.3423796273],"iteration":500,"passed_time":0.640075821,"remaining_time":0.6375206281},
{"learn":[0.3423796273],"iteration":501,"passed_time":0.6410314904,"remaining_time":0.6359236698},
{"learn":[0.3423796273],"iteration":502,"passed_time":0.6420908732,"remaining_time":0.6344317376},
{"learn":[0.3423796273],"iteration":503,"passed_time":0.6432319863,"remaining_time":0.6330219547},
{"learn":[0.3423796273],"iteration":504,"passed_time":0.6440842184,"remaining_time":0.6313300755},
{"learn":[0.3423796273],"iteration":505,"passed_time":0.6449710381,"remaining_time":0.6296752822},
{"learn":[0.3423796273],"iteration":506,"passed_time":0.6460883069,"remaining_time":0.6282476041},
{"learn":[0.3423796273],"iteration":507,"passed_time":0.6472226607,"remaining_time":0.626837695},
{"learn":[0.3423796273],"iteration":508,"passed_time":0.6484710582,"remaining_time":0.6255388793},
{"learn":[0.3423796273],"iteration":509,"passed_time":0.6497723069,"remaining_time":0.62429104},
{"learn":[0.3423796273],"iteration":510,"passed_time":0.6509934824,"remaining_time":0.6229663658},
{"learn":[0.3423796273],"iteration":511,"passed_time":0.6521819629,"remaining_time":0.6216109334},
{"learn":[0.3423796273],"iteration":512,"passed_time":0.6532895993,"remaining_time":0.6201794052},
{"learn":[0.3423796273],"iteration":513,"passed_time":0.6542626349,"remaining_time":0.6186218688},
{"learn":[0.3423796273],"iteration":514,"passed_time":0.6554101742,"remaining_time":0.6172309408},
{"learn":[0.3423796273],"iteration":515,"passed_time":0.6565069177,"remaining_time":0.6157933104},
{"learn":[0.3423796273],"iteration":516,"passed_time":0.6574956082,"remaining_time":0.6142560517},
{"learn":[0.3423796273],"iteration":517,"passed_time":0.6585543174,"remaining_time":0.6127860637},
{"learn":[0.3423796273],"iteration":518,"passed_time":0.6595771869,"remaining_time":0.6112844449},
{"learn":[0.3423796273],"iteration":519,"passed_time":0.660473728,"remaining_time":0.6096680566},
{"learn":[0.3423796273],"iteration":520,"passed_time":0.6613664591,"remaining_time":0.6080509288},
{"learn":[0.3423796273],"iteration":521,"passed_time":0.6625164244,"remaining_time":0.6066721281},
{"learn":[0.3423796273],"iteration":522,"passed_time":0.6636527441,"remaining_time":0.605281757},
{"learn":[0.3423796273],"iteration":523,"passed_time":0.6648091145,"remaining_time":0.6039105697},
{"learn":[0.3423796273],"iteration":524,"passed_time":0.6659408122,"remaining_time":0.6025178777},
{"learn":[0.3423796273],"iteration":525,"passed_time":0.6670447744,"remaining_time":0.6011011845},
{"learn":[0.3423796273],"iteration":526,"passed_time":0.6686064183,"remaining_time":0.6000964627},
{"learn":[0.3423796273],"iteration":527,"passed_time":0.6697644937,"remaining_time":0.5987288655},
{"learn":[0.3423796273],"iteration":528,"passed_time":0.6709625702,"remaining_time":0.5973976759},
{"learn":[0.3423796273],"iteration":529,"passed_time":0.6719882803,"remaining_time":0.5959141354},
{"learn":[0.3423796273],"iteration":530,"passed_time":0.6729501335,"remaining_time":0.5943759183},
{"learn":[0.3423796273],"iteration":531,"passed_time":0.6739490318,"remaining_time":0.5928724565},
{"learn":[0.3423796273],"iteration":532,"passed_time":0.6751766404,"remaining_time":0.5915712778},
{"learn":[0.3423796273],"iteration":533,"passed_time":0.675981296,"remaining_time":0.5899012808},
{"learn":[0.3423796273],"iteration":534,"passed_time":0.6769366931,"remaining_time":0.588365537},
{"learn":[0.3423796273],"iteration":535,"passed_time":0.6780049152,"remaining_time":0.5869296281},
{"learn":[0.3423796273],"iteration":536,"passed_time":0.6789916913,"remaining_time":0.585424866},
{"learn":[0.3423796273],"iteration":537,"passed_time":0.6801400425,"remaining_time":0.58406078},
{"learn":[0.3423796273],"iteration":538,"passed_time":0.6813411427,"remaining_time":0.58274261},
{"learn":[0.3423796273],"iteration":539,"passed_time":0.6823655552,"remaining_time":0.5812743619},
{"learn":[0.3423796273],"iteration":540,"passed_time":0.6833689005,"remaining_time":0.5797898805},
{"learn":[0.3423796273],"iteration":541,"passed_time":0.6842175578,"remaining_time":0.5781764603},
{"learn":[0.3423796273],"iteration":542,"passed_time":0.6852810176,"remaining_time":0.5767466391},
{"learn":[0.3423796273],"iteration":543,"passed_time":0.6864096882,"remaining_time":0.5753728268},
{"learn":[0.3423796273],"iteration":544,"passed_time":0.6876251386,"remaining_time":0.5740723634},
{"learn":[0.3423796273],"iteration":545,"passed_time":0.6887736525,"remaining_time":0.5727165536},
{"learn":[0.3423796273],"iteration":546,"passed_time":0.6899495011,"remaining_time":0.5713841389},
{"learn":[0.3423796273],"iteration":547,"passed_time":0.6909632494,"remaining_time":0.5699185926},
{"learn":[0.3423796273],"iteration":548,"passed_time":0.6919701687,"remaining_time":0.5684490821},
{"learn":[0.3423796273],"iteration":549,"passed_time":0.6930595229,"remaining_time":0.5670487005},
{"learn":[0.3423796273],"iteration":550,"passed_time":0.6942391216,"remaining_time":0.5657229865},
{"learn":[0.3423796273],"iteration":551,"passed_time":0.6953031563,"remaining_time":0.5643040109},
{"learn":[0.3423796273],"iteration":552,"passed_time":0.6965261618,"remaining_time":0.5630148179},
{"learn":[0.3423796273],"iteration":553,"passed_time":0.6976113071,"remaining_time":0.561614879},
{"learn":[0.3423796273],"iteration":554,"passed_time":0.6986082648,"remaining_time":0.5601453655},
{"learn":[0.3423796273],"iteration":555,"passed_time":0.6996853856,"remaining_time":0.5587415669},
{"learn":[0.3423796273],"iteration":556,"passed_time":0.7007158446,"remaining_time":0.5573018297},
{"learn":[0.3423796273],"iteration":557,"passed_time":0.7018166742,"remaining_time":0.5559193011},
{"learn":[0.3423796273],"iteration":558,"passed_time":0.7029088706,"remaining_time":0.5545309695},
{"learn":[0.3423796273],"iteration":559,"passed_time":0.7040486185,"remaining_time":0.5531810574},
{"learn":[0.3423796273],"iteration":560,"passed_time":0.705176764,"remaining_time":0.5518228153},
{"learn":[0.3423796273],"iteration":561,"passed_time":0.7063143935,"remaining_time":0.5504727836},
{"learn":[0.3423796273],"iteration":562,"passed_time":0.707291284,"remaining_time":0.5489987409},
{"learn":[0.3423796273],"iteration":563,"passed_time":0.7083149858,"remaining_time":0.5475626486},
{"learn":[0.3423796273],"iteration":564,"passed_time":0.709327602,
{"learn":[0.4350554053],"itera,
{"learn":[0.3423796273],"iteration":565,"passed_time":0.7106904617,"remaining_time":0.5449463964},
{"learn":[0.3423796273],"iteration":566,"passed_time":0.7119200668,"remaining_time":0.5436708799},
{"learn":[0.3423796273],"iteration":567,"passed_time":0.7129510367,"remaining_time":0.5422444504},
{"learn":[0.3423796273],"iteration":568,"passed_time":0.714051772,"remaining_time":0.5408722561},
{"learn":[0.3423796273],"iteration":569,"passed_time":0.7151459256,
{"learn":[0.435053349],"itera,
{"learn":[0.3423796273],"iteration":570,"passed_time":0.716323502,
{"learn":[0.4350514876],"itera,
{"learn":[0.3423796273],"iteration":571,"passed_time":0.717369439,
{"learn":[0.4350510089],"itera,
{"learn":[0.3423796273],"iteration":572,"passed_time":0.718532092,
{"learn":[0.4350508181],"itera,
{"learn":[0.3423796273],"iteration":573,"passed_time":0.719693274,
{"learn":[0.4350504355],"itera,
{"learn":[0.3423796273],"iteration":574,"passed_time":0.720720222,
{"learn":[0.4350492428],"itera,
{"learn":[0.3423796273],"iteration":575,"passed_time":0.721843321,
{"learn":[0.4350489072],"itera,
{"learn":[0.3423796273],"iteration":576,"passed_time":0.722867747,
{"learn":[0.4350489072],"iter,
{"learn":[0.3423796273],"iteration":577,"passed_time":0.7239512242,
{"learn":[0.4350489072],"iter,
{"learn":[0.3423796273],"iteration":578,"passed_time":0.725102864,
{"learn":[0.4350489072],"itera,
{"learn":[0.3423796273],"iteration":579,"passed_time":0.726187,
{"learn":[0.4350489072],"iterati,
{"learn":[0.3423796273],"iteration":580,"passed_time":0.7272765819,"remaining_time":0.5244903405},
{"learn":[0.3423796273],"iteration":581,"passed_time":0.7283843191,"remaining_time":0.5231351296},
{"learn":[0.3423796273],"iteration":582,"passed_time":0.7295364155,"remaining_time":0.5218124962},
{"learn":[0.3423796273],"iteration":583,"passed_time":0.7305383458,"remaining_time":0.5203834792},
{"learn":[0.3423796273],"iteration":584,"passed_time":0.7315015101,"remaining_time":0.5189284217},
{"learn":[0.3423796273],"iteration":585,"passed_time":0.7326746339,"remaining_time":0.5176233761},
{"learn":[0.3423796273],"iteration":586,"passed_time":0.7337518064,"remaining_time":0.5162512709},
{"learn":[0.3423796273],"iteration":587,"passed_time":0.7348673787,"remaining_time":0.5149070748},
{"learn":[0.3423796273],"iteration":588,"passed_time":0.7361864789,"remaining_time":0.5137056754},
{"learn":[0.3423796273],"iteration":589,"passed_time":0.737435724,"remaining_time":0.5124553336},
{"learn":[0.3423796273],"iteration":590,"passed_time":0.7388234879,"remaining_time":0.5113008571},
{"learn":[0.3423796273],"iteration":591,"passed_time":0.7398731408,"remaining_time":0.50991257},
{"learn":[0.3423796273],"iteration":592,"passed_time":0.7410092092,"remaining_time":0.5085847355},
{"learn":[0.3423796273],"iteration":593,"passed_time":0.7422783257,"remaining_time":0.5073484852},
{"learn":[0.3423796273],"iteration":594,"passed_time":0.7433594911,"remaining_time":0.5059841914},
{"learn":[0.3423796273],"iteration":595,"passed_time":0.7443562448,"remaining_time":0.504563629},
{"learn":[0.3423796273],"iteration":596,"passed_time":0.7454320507,"remaining_time":0.50319785},
{"learn":[0.3423796273],"iteration":597,"passed_time":0.7463940873,"remaining_time":0.5017565603},
{"learn":[0.3423796273],"iteration":598,"passed_time":0.7474403503,"remaining_time":0.5003732562},
{"learn":[0.3423796273],"iteration":599,"passed_time":0.7485972984,"remaining_time":0.4990648656},
{"learn":[0.3423796273],"iteration":600,"passed_time":0.7495936712,"remaining_time":0.4976503741},
{"learn":[0.3423796273],"iteration":601,"passed_time":0.7508125373,"remaining_time":0.4963843685},
{"learn":[0.3423796273],"iteration":602,"passed_time":0.7519200808,"remaining_time":0.4950452273},
{"learn":[0.3423796273],"iteration":603,"passed_time":0.7531276099,"remaining_time":0.4937724065},
{"learn":[0.3423796273],"iteration":604,"passed_time":0.7541783737,"remaining_time":0.4923974506},
{"learn":[0.3423796273],"iteration":605,"passed_time":0.75517937,"remaining_time":0.4909912076},
{"learn":[0.3423796273],"iteration":606,"passed_time":0.7562513061,"remaining_time":0.4896322295},
{"learn":[0.3423796273],"iteration":607,"passed_time":0.757337492,"remaining_time":0.488283383},
{"learn":[0.3423796273],"iteration":608,"passed_time":0.7584126002,"remaining_time":0.4869282868},
{"learn":[0.3423796273],"iteration":609,"passed_time":0.7594815223,"remaining_time":0.4855701536},
{"learn":[0.3423796273],"iteration":610,"passed_time":0.7605912966,"remaining_time":0.4842389761},
{"learn":[0.3423796273],"iteration":611,"passed_time":0.7616425129,"remaining_time":0.4828713971},
{"learn":[0.3423796273],"iteration":612,"passed_time":0.7627584032,"remaining_time":0.4815456803},
{"learn":[0.3423796273],"iteration":613,"passed_time":0.7638658086,"remaining_time":0.4802153129},
{"learn":[0.3423796273],"iteration":614,"passed_time":0.7652224436,"remaining_time":0.4790416924},
{"learn":[0.3423796273],"iteration":615,"passed_time":0.7664462711,"remaining_time":0.4777846885},
{"learn":[0.3423796273],"iteration":616,"passed_time":0.7676282387,"remaining_time":0.4765018078},
{"learn":[0.3423796273],"iteration":617,"passed_time":0.7688338388,"remaining_time":0.4752338615},
{"learn":[0.3423796273],"iteration":618,"passed_time":0.7699331058,"remaining_time":0.4739006677},
{"learn":[0.3423796273],"iteration":619,"passed_time":0.7711506797,"remaining_time":0.4726407391},
{"learn":[0.3423796273],"iteration":620,"passed_time":0.7721262906,"remaining_time":0.4712332756},
{"learn":[0.3423796273],"iteration":621,"passed_time":0.7732623402,"remaining_time":0.4699247019},
{"learn":[0.3423796273],"iteration":622,"passed_time":0.7742392303,"remaining_time":0.4685203689},
{"learn":[0.3423796273],"iteration":623,"passed_time":0.7753757862,"remaining_time":0.4672136147},
{"learn":[0.3423796273],"iteration":624,"passed_time":0.776594897,"remaining_time":0.4659569382},
{"learn":[0.3423796273],"iteration":625,"passed_time":0.7777406404,"remaining_time":0.4646565487},
{"learn":[0.3423796273],"iteration":626,"passed_time":0.7787117824,"remaining_time":0.4632527828},
{"learn":[0.3423796273],"iteration":627,"passed_time":0.7798253268,"remaining_time":0.4619347477},
{"learn":[0.3423796273],"iteration":628,"passed_time":0.7808795261,"remaining_time":0.4605823596},
{"learn":[0.3423796273],"iteration":629,"passed_time":0.7819374982,"remaining_time":0.4592331339},
{"learn":[0.3423796273],"iteration":630,"passed_time":0.7831182326,"remaining_time":0.457956621},
{"learn":[0.3423796273],"iteration":631,"passed_time":0.7842999198,"remaining_time":0.456680966},
{"learn":[0.3423796273],"iteration":632,"passed_time":0.7853835612,"remaining_time":0.455348763},
{"learn":[0.3423796273],"iteration":633,"passed_time":0.7865060207,"remaining_time":0.4540397533},
{"learn":[0.3423796273],"iteration":634,"passed_time":0.7876168476,"remaining_time":0.4527246447},
{"learn":[0.3423796273],"iteration":635,"passed_time":0.7887317398,"remaining_time":0.4514125052},
{"learn":[0.3423796273],"iteration":636,"passed_time":0.7897618885,"remaining_time":0.4500526931},
{"learn":[0.3423796273],"iteration":637,"passed_time":0.7907193829,"remaining_time":0.4486526906},
{"learn":[0.3423796273],"iteration":638,"passed_time":0.7917344043,"remaining_time":0.4472865727},
{"learn":[0.3423796273],"iteration":639,"passed_time":0.7928751011,"remaining_time":0.4459922444},
{"learn":[0.3423796273],"iteration":640,"passed_time":0.7939528068,"remaining_time":0.4446631165},
{"learn":[0.3423796273],"iteration":641,"passed_time":0.795261619,"remaining_time":0.4434636443},
{"learn":[0.3423796273],"iteration":642,"passed_time":0.7962333851,"remaining_time":0.4420767006},
{"learn":[0.3423796273],"iteration":643,"passed_time":0.7973385125,"remaining_time":0.4407647678},
{"learn":[0.3423796273],"iteration":644,"passed_time":0.7988048622,"remaining_time":0.4396522885},
{"learn":[0.3423796273],"iteration":645,"passed_time":0.8000734877,"remaining_time":0.4384303632},
{"learn":[0.3423796273],"iteration":646,"passed_time":0.8011372485,"remaining_time":0.4370965204},
{"learn":[0.3423796273],"iteration":647,"passed_time":0.8022004309,"remaining_time":0.435763197},
{"learn":[0.3423796273],"iteration":648,"passed_time":0.8032242535,"remaining_time":0.4344094191},
{"learn":[0.3423796273],"iteration":649,"passed_time":0.8043889373,"remaining_time":0.4331325047},
{"learn":[0.3423796273],"iteration":650,"passed_time":0.8054831025,"remaining_time":0.4318181302},
{"learn":[0.3423796273],"iteration":651,"passed_time":0.8065875265,"remaining_time":0.4305099068},
{"learn":[0.3423796273],"iteration":652,"passed_time":0.8077670707,"remaining_time":0.429242226},
{"learn":[0.3423796273],"iteration":653,"passed_time":0.8087909263,"remaining_time":0.4278924473},
{"learn":[0.3423796273],"iteration":654,"passed_time":0.809876507,"remaining_time":0.4265761754},
{"learn":[0.3423796273],"iteration":655,"passed_time":0.8110153113,"remaining_time":0.4252885169},
{"learn":[0.3423796273],"iteration":656,"passed_time":0.8121003504,"remaining_time":0.4239732423},
{"learn":[0.3423796273],"iteration":657,"passed_time":0.8133303598,"remaining_time":0.4227340168},
{"learn":[0.3423796273],"iteration":658,"passed_time":0.8142777875,"remaining_time":0.4213485972},
{"learn":[0.3423796273],"iteration":659,"passed_time":0.8151905848,"remaining_time":0.4199466649},
{"learn":[0.3423796273],"iteration":660,"passed_time":0.816253381,"remaining_time":0.4186231409},
{"learn":[0.3423796273],"iteration":661,"passed_time":0.817271037,"remaining_time":0.4172773573},
{"learn":[0.3423796273],"iteration":662,"passed_time":0.8182738373,"remaining_time":0.4159250123},
{"learn":[0.3423796273],"iteration":663,"passed_time":0.8193666746,"remaining_time":0.4146192811},
{"learn":[0.3423796273],"iteration":664,"passed_time":0.8202932779,"remaining_time":0.4132304482},
{"learn":[0.3423796273],"iteration":665,"passed_time":0.821394664,"remaining_time":0.4119306573},
{"learn":[0.3423796273],"iteration":666,"passed_time":0.8225575597,"remaining_time":0.41066217},
{"learn":[0.3423796273],"iteration":667,"passed_time":0.8236391428,"remaining_time":0.4093535859},
{"learn":[0.3423796273],"iteration":668,"passed_time":0.8247650498,"remaining_time":0.4080676106},
{"learn":[0.3423796273],"iteration":669,"passed_time":0.8257283794,"remaining_time":0.4067020376},
{"learn":[0.3423796273],"iteration":670,"passed_time":0.8267393695,"remaining_time":0.4053610321},
{"learn":[0.3423796273],"iteration":671,"passed_time":0.827989185,"remaining_time":0.4041375784},
{"learn":[0.3423796273],"iteration":672,"passed_time":0.829117823,"remaining_time":0.4028551681},
{"learn":[0.3423796273],"iteration":673,"passed_time":0.8303316287,"remaining_time":0.4016144079},
{"learn":[0.3423796273],"iteration":674,"passed_time":0.8314484989,"remaining_time":0.400327055},
{"learn":[0.3423796273],"iteration":675,"passed_time":0.8326688479,"remaining_time":0.3990898028},
{"learn":[0.3423796273],"iteration":676,"passed_time":0.8338291974,"remaining_time":0.3978239745},
{"learn":[0.3423796273],"iteration":677,"passed_time":0.8349414714,"remaining_time":0.3965356251},
{"learn":[0.3423796273],"iteration":678,"passed_time":0.8361825225,"remaining_time":0.3953086741},
{"learn":[0.3423796273],"iteration":679,"passed_time":0.8374027065,"remaining_time":0.3940718619},
{"learn":[0.3423796273],"iteration":680,"passed_time":0.8384600879,"remaining_time":0.392758837},
{"learn":[0.3423796273],"iteration":681,"passed_time":0.8396865217,"remaining_time":0.3915253869},
{"learn":[0.3423796273],"iteration":682,"passed_time":0.8407137503,"remaining_time":0.3901995005},
{"learn":[0.3423796273],"iteration":683,"passed_time":0.8419632662,"remaining_time":0.3889771815},
{"learn":[0.3423796273],"iteration":684,"passed_time":0.843189626,"remaining_time":0.3877441346},
{"learn":[0.3423796273],"iteration":685,"passed_time":0.8442765564,"remaining_time":0.3864472867},
{"learn":[0.3423796273],"iteration":686,"passed_time":0.84526283,"remaining_time":0.3851051904},
{"learn":[0.3423796273],"iteration":687,"passed_time":0.8463643527,"remaining_time":0.3838163925},
{"learn":[0.3423796273],"iteration":688,"passed_time":0.8474787026,"remaining_time":0.3825339282},
{"learn":[0.3423796273],"iteration":689,"passed_time":0.8486157533,"remaining_time":0.38126215},
{"learn":[0.3423796273],"iteration":690,"passed_time":0.850057943,"remaining_time":0.3801272133},
{"learn":[0.3423796273],"iteration":691,"passed_time":0.8511919789,"remaining_time":0.3788542334},
{"learn":[0.3423796273],"iteration":692,"passed_time":0.8525635154,"remaining_time":0.3776868676},
{"learn":[0.3423796273],"iteration":693,"passed_time":0.8537061009,"remaining_time":0.3764179638},
{"learn":[0.3423796273],"iteration":694,"passed_time":0.8549928222,"remaining_time":0.3752126773},
{"learn":[0.3423796273],"iteration":695,"passed_time":0.8560979109,"remaining_time":0.3739278231},
{"learn":[0.3423796273],"iteration":696,"passed_time":0.8571877556,"remaining_time":0.3726368579},
{"learn":[0.3423796273],"iteration":697,"passed_time":0.8582004218,"remaining_time":0.3713130765},
{"learn":[0.3423796273],"iteration":698,"passed_time":0.8593954249,"remaining_time":0.3700687023},
{"learn":[0.3423796273],"iteration":699,"passed_time":0.8604442904,"remaining_time":0.3687618387},
{"learn":[0.3423796273],"iteration":700,"passed_time":0.861580358,"remaining_time":0.3674929059},
{"learn":[0.3423796273],"iteration":701,"passed_time":0.8627103914,"remaining_time":0.3662217901},
{"learn":[0.3423796273],"iteration":702,"passed_time":0.8638068925,"remaining_time":0.3649369091},
{"learn":[0.3423796273],"iteration":703,"passed_time":0.8648133174,"remaining_time":0.3636146903},
{"learn":[0.3423796273],"iteration":704,"passed_time":0.8659238013,"remaining_time":0.3623369098},
{"learn":[0.3423796273],"iteration":705,"passed_time":0.8669331329,"remaining_time":0.3610174803},
{"learn":[0.3423796273],"iteration":706,"passed_time":0.8680509425,"remaining_time":0.3597438842},
{"learn":[0.3423796273],"iteration":707,"passed_time":0.869308822,"remaining_time":0.3585284972},
{"learn":[0.3423796273],"iteration":708,"passed_time":0.8704999165,"remaining_time":0.3572855793},
{"learn":[0.3423796273],"iteration":709,"passed_time":0.8715630801,"remaining_time":0.3559905539},
{"learn":[0.3423796273],"iteration":710,"passed_time":0.8727518901,"remaining_time":0.3547472521},
{"learn":[0.3423796273],"iteration":711,"passed_time":0.8737826411,"remaining_time":0.3534401694},
{"learn":[0.3423796273],"iteration":712,"passed_time":0.874761258,"remaining_time":0.3521128766},
{"learn":[0.3423796273],"iteration":713,"passed_time":0.8759014558,"remaining_time":0.3508512834},
{"learn":[0.3423796273],"iteration":714,"passed_time":0.8769368107,"remaining_time":0.3495482392},
{"learn":[0.3423796273],"iteration":715,"passed_time":0.8782894313,"remaining_time":0.3483717856},
{"learn":[0.3423796273],"iteration":716,"passed_time":0.8795991196,"remaining_time":0.3471778952},
{"learn":[0.3423796273],"iteration":717,"passed_time":0.8808323704,"remaining_time":0.3459536608},
{"learn":[0.3423796273],"iteration":718,"passed_time":0.8818751411,"remaining_time":0.3446549578},
{"learn":[0.3423796273],"iteration":719,"passed_time":0.882948572,"remaining_time":0.3433688891},
{"learn":[0.3423796273],"iteration":720,"passed_time":0.8840051022,"remaining_time":0.3420768704},
{"learn":[0.3423796273],"iteration":721,"passed_time":0.8852314789,"remaining_time":0.3408509018},
{"learn":[0.3423796273],"iteration":722,"passed_time":0.8862144818,"remaining_time":0.3395316894},
{"learn":[0.3423796273],"iteration":723,"passed_time":0.8875967957,"remaining_time":0.3383656293},
{"learn":[0.3423796273],"iteration":724,"passed_time":0.8885811492,"remaining_time":0.3370480221},
{"learn":[0.3423796273],"iteration":725,"passed_time":0.8896900597,"remaining_time":0.3357783421},
{"learn":[0.3423796273],"iteration":726,"passed_time":0.890659478,"remaining_time":0.3344567228},
{"learn":[0.3423796273],"iteration":727,"passed_time":0.8917606881,"remaining_time":0.333185312},
{"learn":[0.3423796273],"iteration":728,"passed_time":0.8927995652,"remaining_time":0.3318911964},
{"learn":[0.3423796273],"iteration":729,"passed_time":0.8938074534,"remaining_time":0.3305863184},
{"learn":[0.3423796273],"iteration":730,"passed_time":0.8950101937,"remaining_time":0.3293539564},
{"learn":[0.3423796273],"iteration":731,"passed_time":0.8960764116,"remaining_time":0.3280716917},
{"learn":[0.3423796273],"iteration":732,"passed_time":0.8971990668,"remaining_time":0.3268105741},
{"learn":[0.3423796273],"iteration":733,"passed_time":0.8983417501,"remaining_time":0.325557092},
{"learn":[0.3423796273],"iteration":734,"passed_time":0.8994231514,"remaining_time":0.3242818165},
{"learn":[0.3423796273],"iteration":735,"passed_time":0.9005623033,"remaining_time":0.3230277827},
{"learn":[0.3423796273],"iteration":736,"passed_time":0.9015674168,"remaining_time":0.3217262288},
{"learn":[0.3423796273],"iteration":737,"passed_time":0.9027088118,"remaining_time":0.32047386},
{"learn":[0.3423796273],"iteration":738,"passed_time":0.9039944364,"remaining_time":0.3192727306},
{"learn":[0.3423796273],"iteration":739,"passed_time":0.9052195013,"remaining_time":0.318050095},
{"learn":[0.3423796273],"iteration":740,"passed_time":0.90636935,"remaining_time":0.3168011628},
{"learn":[0.3423796273],"iteration":741,"passed_time":0.9075045653,"remaining_time":0.3155474095},
{"learn":[0.3423796273],"iteration":742,"passed_time":0.9087277607,"remaining_time":0.3143244071},
{"learn":[0.3423796273],"iteration":743,"passed_time":0.9099919096,"remaining_time":0.3131154958},
{"learn":[0.3423796273],"iteration":744,"passed_time":0.9112140912,"remaining_time":0.3118920715},
{"learn":[0.3423796273],"iteration":745,"passed_time":0.9122656953,"remaining_time":0.3106105719},
{"learn":[0.3423796273],"iteration":746,"passed_time":0.9133851224,"remaining_time":0.3093526586},
{"learn":[0.3423796273],"iteration":747,"passed_time":0.9144900512,"remaining_time":0.3080902312},
{"learn":[0.3423796273],"iteration":748,"passed_time":0.9154929577,"remaining_time":0.3067940352},
{"learn":[0.3423796273],"iteration":749,"passed_time":0.916818051,"remaining_time":0.305606017},
{"learn":[0.3423796273],"iteration":750,"passed_time":0.9178751942,"remaining_time":0.3043287928},
{"learn":[0.3423796273],"iteration":751,"passed_time":0.9189856241,"remaining_time":0.3030697271},
{"learn":[0.3423796273],"iteration":752,"passed_time":0.9201525836,"remaining_time":0.3018295991},
{"learn":[0.3423796273],"iteration":753,"passed_time":0.9212758682,"remaining_time":0.3005754159},
{"learn":[0.3423796273],"iteration":754,"passed_time":0.9223999606,"remaining_time":0.2993218415},
{"learn":[0.3423796273],"iteration":755,"passed_time":0.9233942058,"remaining_time":0.2980267013},
{"learn":[0.3423796273],"iteration":756,"passed_time":0.924482937,"remaining_time":0.2967626865},
{"learn":[0.3423796273],"iteration":757,"passed_time":0.9254787552,"remaining_time":0.2954694707},
{"learn":[0.3423796273],"iteration":758,"passed_time":0.9265643765,"remaining_time":0.294205553},
{"learn":[0.3423796273],"iteration":759,"passed_time":0.927633724,"remaining_time":0.2929369655},
{"learn":[0.3423796273],"iteration":760,"passed_time":0.9287509363,"remaining_time":0.291683934},
{"learn":[0.3423796273],"iteration":761,"passed_time":0.9297899903,"remaining_time":0.2904068474},
{"learn":[0.3423796273],"iteration":762,"passed_time":0.9308249524,"remaining_time":0.2891291136},
{"learn":[0.3423796273],"iteration":763,"passed_time":0.9318052435,"remaining_time":0.2878351276},
{"learn":[0.3423796273],"iteration":764,"passed_time":0.9330820531,"remaining_time":0.286633049},
{"learn":[0.3423796273],"iteration":765,"passed_time":0.9340406686,"remaining_time":0.2853335724},
{"learn":[0.3423796273],"iteration":766,"passed_time":0.9351076288,"remaining_time":0.2840678977},
{"learn":[0.3423796273],"iteration":767,"passed_time":0.9361523621,"remaining_time":0.2827960261},
{"learn":[0.3423796273],"iteration":768,"passed_time":0.93731627,"remaining_time":0.281560544},
{"learn":[0.3423796273],"iteration":769,"passed_time":0.9383748826,"remaining_time":0.2802937961},
{"learn":[0.3423796273],"iteration":770,"passed_time":0.9393874841,"remaining_time":0.279013922},
{"learn":[0.3423796273],"iteration":771,"passed_time":0.940565697,"remaining_time":0.2777836514},
{"learn":[0.3423796273],"iteration":772,"passed_time":0.9417313708,"remaining_time":0.2765498333},
{"learn":[0.3423796273],"iteration":773,"passed_time":0.9429174383,"remaining_time":0.2753221461},
{"learn":[0.3423796273],"iteration":774,"passed_time":0.9440447204,"remaining_time":0.2740774995},
{"learn":[0.3423796273],"iteration":775,"passed_time":0.9451574374,"remaining_time":0.272828951},
{"learn":[0.3423796273],"iteration":776,"passed_time":0.9464256425,"remaining_time":0.2716253774},
{"learn":[0.3423796273],"iteration":777,"passed_time":0.9476412406,"remaining_time":0.2704066265},
{"learn":[0.3423796273],"iteration":778,"passed_time":0.948555306,"remaining_time":0.2691023397},
{"learn":[0.3423796273],"iteration":779,"passed_time":0.9497493961,"remaining_time":0.2678780348},
{"learn":[0.3423796273],"iteration":780,"passed_time":0.9511465619,"remaining_time":0.2667107517},
{"learn":[0.3423796273],"iteration":781,"passed_time":0.9524006879,"remaining_time":0.2655030051},
{"learn":[0.3423796273],"iteration":782,"passed_time":0.9534345963,"remaining_time":0.2642341091},
{"learn":[0.3423796273],"iteration":783,"passed_time":0.9546534214,"remaining_time":0.2630167589},
{"learn":[0.3423796273],"iteration":784,"passed_time":0.9558400086,"remaining_time":0.2617905756},
{"learn":[0.3423796273],"iteration":785,"passed_time":0.9568872608,"remaining_time":0.260526557},
{"learn":[0.3423796273],"iteration":786,"passed_time":0.957898338,"remaining_time":0.2592532986},
{"learn":[0.3423796273],"iteration":787,"passed_time":0.9588742005,"remaining_time":0.2579712316},
{"learn":[0.3423796273],"iteration":788,"passed_time":0.959918777,"remaining_time":0.2567083168},
{"learn":[0.3423796273],"iteration":789,"passed_time":0.9612143685,"remaining_time":0.2555126802},
{"learn":[0.3423796273],"iteration":790,"passed_time":0.9622304984,"remaining_time":0.2542429509},
{"learn":[0.3423796273],"iteration":791,"passed_time":0.9632893803,"remaining_time":0.2529850898},
{"learn":[0.3423796273],"iteration":792,"passed_time":0.964328501,"remaining_time":0.2517225721},
{"learn":[0.3423796273],"iteration":793,"passed_time":0.9652596721,"remaining_time":0.2504326101},
{"learn":[0.3423796273],"iteration":794,"passed_time":0.9664422768,"remaining_time":0.2492083858},
{"learn":[0.3423796273],"iteration":795,"passed_time":0.9674404509,"remaining_time":0.247937},
{"learn":[0.3423796273],"iteration":796,"passed_time":0.968457181,"remaining_time":0.246671026},
{"learn":[0.3423796273],"iteration":797,"passed_time":0.9694908578,"remaining_time":0.2454099665},
{"learn":[0.3423796273],"iteration":798,"passed_time":0.9706972779,"remaining_time":0.2441929322},
{"learn":[0.3423796273],"iteration":799,"passed_time":0.9717863275,"remaining_time":0.2429465819},
{"learn":[0.3423796273],"iteration":800,"passed_time":0.9728737366,"remaining_time":0.2417002167},
{"learn":[0.3423796273],"iteration":801,"passed_time":0.9740077269,"remaining_time":0.240465748},
{"learn":[0.3423796273],"iteration":802,"passed_time":0.9750684303,"remaining_time":0.2392135502},
{"learn":[0.3423796273],"iteration":803,"passed_time":0.9761591971,"remaining_time":0.2379691575},
{"learn":[0.3423796273],"iteration":804,"passed_time":0.9773092181,"remaining_time":0.2367395},
{"learn":[0.3423796273],"iteration":805,"passed_time":0.9784369106,"remaining_time":0.2355046658},
{"learn":[0.3423796273],"iteration":806,"passed_time":0.9795907948,"remaining_time":0.2342763611},
{"learn":[0.3423796273],"iteration":807,"passed_time":0.9808459345,"remaining_time":0.2330723013},
{"learn":[0.3423796273],"iteration":808,"passed_time":0.9819606445,"remaining_time":0.2318349606},
{"learn":[0.3423796273],"iteration":809,"passed_time":0.9830098299,"remaining_time":0.2305825527},
{"learn":[0.3423796273],"iteration":810,"passed_time":0.9842480457,"remaining_time":0.2293746987},
{"learn":[0.3423796273],"iteration":811,"passed_time":0.985387379,"remaining_time":0.2281438759},
{"learn":[0.3423796273],"iteration":812,"passed_time":0.9865264388,"remaining_time":0.2269132153},
{"learn":[0.3423796273],"iteration":813,"passed_time":0.987619711,"remaining_time":0.2256723173},
{"learn":[0.3423796273],"iteration":814,"passed_time":0.9888064191,"remaining_time":0.2244529908},
{"learn":[0.3423796273],"iteration":815,"passed_time":0.9900200284,"remaining_time":0.2232398103},
{"learn":[0.3423796273],"iteration":816,"passed_time":0.9911471168,"remaining_time":0.2220072489},
{"learn":[0.3423796273],"iteration":817,"passed_time":0.9922655079,"remaining_time":0.2207730103},
{"learn":[0.3423796273],"iteration":818,"passed_time":0.9934649726,"remaining_time":0.219556972},
{"learn":[0.3423796273],"iteration":819,"passed_time":0.9944378287,"remaining_time":0.2182912307},
{"learn":[0.3423796273],"iteration":820,"passed_time":0.9956457762,"remaining_time":0.2170774591},
{"learn":[0.3423796273],"iteration":821,"passed_time":0.9967492985,"remaining_time":0.215841089},
{"learn":[0.3423796273],"iteration":822,"passed_time":0.9978331707,"remaining_time":0.2146008156},
{"learn":[0.3423796273],"iteration":823,"passed_time":0.998857047,"remaining_time":0.2133481071},
{"learn":[0.3423796273],"iteration":824,"passed_time":1.000207459,"remaining_time":0.2121652185},
{"learn":[0.3423796273],"iteration":825,"passed_time":1.001343767,"remaining_time":0.2109368226},
{"learn":[0.3423796273],"iteration":826,"passed_time":1.002471862,"remaining_time":0.2097069313},
{"learn":[0.3423796273],"iteration":827,"passed_time":1.003466456,"remaining_time":0.2084495537},
{"learn":[0.3423796273],"iteration":828,"passed_time":1.004510838,"remaining_time":0.20720308},
{"learn":[0.3423796273],"iteration":829,"passed_time":1.005526178,"remaining_time":0.205951145},
{"learn":[0.3423796273],"iteration":830,"passed_time":1.006745968,"remaining_time":0.2047413581},
{"learn":[0.3423796273],"iteration":831,"passed_time":1.007875162,"remaining_time":0.2035132539},
{"learn":[0.3423796273],"iteration":832,"passed_time":1.008804332,"remaining_time":0.2022452863},
{"learn":[0.3423796273],"iteration":833,"passed_time":1.00986139,"remaining_time":0.2010035861},
{"learn":[0.3423796273],"iteration":834,"passed_time":1.010850121,"remaining_time":0.1997488263},
{"learn":[0.3423796273],"iteration":835,"passed_time":1.011904575,"remaining_time":0.198507596},
{"learn":[0.3423796273],"iteration":836,"passed_time":1.013195453,"remaining_time":0.197312854},
{"learn":[0.3423796273],"iteration":837,"passed_time":1.014379668,"remaining_time":0.1960972629},
{"learn":[0.3423796273],"iteration":838,"passed_time":1.015579831,"remaining_time":0.1948848067},
{"learn":[0.3423796273],"iteration":839,"passed_time":1.016714652,"remaining_time":0.1936599338},
{"learn":[0.3423796273],"iteration":840,"passed_time":1.017654944,"remaining_time":0.1923984971},
{"learn":[0.3423796273],"iteration":841,"passed_time":1.01886937,"remaining_time":0.1911892642},
{"learn":[0.3423796273],"iteration":842,"passed_time":1.020142697,"remaining_time":0.1899909886},
{"learn":[0.3423796273],"iteration":843,"passed_time":1.021376768,"remaining_time":0.1887852794},
{"learn":[0.3423796273],"iteration":844,"passed_time":1.022649778,"remaining_time":0.1875866456},
{"learn":[0.3423796273],"iteration":845,"passed_time":1.023780977,"remaining_time":0.1863620219},
{"learn":[0.3423796273],"iteration":846,"passed_time":1.024898097,"remaining_time":0.1851350753},
{"learn":[0.3423796273],"iteration":847,"passed_time":1.025951006,"remaining_time":0.1838968785},
{"learn":[0.3423796273],"iteration":848,"passed_time":1.027013619,"remaining_time":0.1826608439},
{"learn":[0.3423796273],"iteration":849,"passed_time":1.028056701,"remaining_time":0.1814217708},
{"learn":[0.3423796273],"iteration":850,"passed_time":1.02911178,"remaining_time":0.1801852588},
{"learn":[0.3423796273],"iteration":851,"passed_time":1.030168945,"remaining_time":0.1789495351},
{"learn":[0.3423796273],"iteration":852,"passed_time":1.031262938,"remaining_time":0.1777205767},
{"learn":[0.3423796273],"iteration":853,"passed_time":1.032315607,"remaining_time":0.1764848696},
{"learn":[0.3423796273],"iteration":854,"passed_time":1.033404086,"remaining_time":0.1752556637},
{"learn":[0.3423796273],"iteration":855,"passed_time":1.034435599,"remaining_time":0.1740172036},
{"learn":[0.3423796273],"iteration":856,"passed_time":1.03559216,"remaining_time":0.172800092},
{"learn":[0.3423796273],"iteration":857,"passed_time":1.036729011,"remaining_time":0.1715798595},
{"learn":[0.3423796273],"iteration":858,"passed_time":1.037811867,"remaining_time":0.1703509583},
{"learn":[0.3423796273],"iteration":859,"passed_time":1.038830999,"remaining_time":0.169112023},
{"learn":[0.3423796273],"iteration":860,"passed_time":1.039944153,"remaining_time":0.1678887772},
{"learn":[0.3423796273],"iteration":861,"passed_time":1.040921019,"remaining_time":0.1666439682},
{"learn":[0.3423796273],"iteration":862,"passed_time":1.041990987,"remaining_time":0.16541456},
{"learn":[0.3423796273],"iteration":863,"passed_time":1.043182592,"remaining_time":0.1642046672},
{"learn":[0.3423796273],"iteration":864,"passed_time":1.044373159,"remaining_time":0.1629946549},
{"learn":[0.3423796273],"iteration":865,"passed_time":1.045467339,"remaining_time":0.161769773},
{"learn":[0.3423796273],"iteration":866,"passed_time":1.046508598,"remaining_time":0.1605370744},
{"learn":[0.3423796273],"iteration":867,"passed_time":1.047672398,"remaining_time":0.1593234523},
{"learn":[0.3423796273],"iteration":868,"passed_time":1.048774284,"remaining_time":0.1581006113},
{"learn":[0.3423796273],"iteration":869,"passed_time":1.049838914,"remaining_time":0.1568724814},
{"learn":[0.3423796273],"iteration":870,"passed_time":1.050901578,"remaining_time":0.1556444359},
{"learn":[0.3423796273],"iteration":871,"passed_time":1.052036698,"remaining_time":0.1544274051},
{"learn":[0.3423796273],"iteration":872,"passed_time":1.053169235,"remaining_time":0.1532101866},
{"learn":[0.3423796273],"iteration":873,"passed_time":1.054195038,"remaining_time":0.1519777743},
{"learn":[0.3423796273],"iteration":874,"passed_time":1.055297927,"remaining_time":0.1507568467},
{"learn":[0.3423796273],"iteration":875,"passed_time":1.056330564,"remaining_time":0.1495262442},
{"learn":[0.3423796273],"iteration":876,"passed_time":1.057303421,"remaining_time":0.1482877089},
{"learn":[0.3423796273],"iteration":877,"passed_time":1.058378723,"remaining_time":0.1470640138},
{"learn":[0.3423796273],"iteration":878,"passed_time":1.059887742,"remaining_time":0.1459003604},
{"learn":[0.3423796273],"iteration":879,"passed_time":1.060921269,"remaining_time":0.1446710821},
{"learn":[0.3423796273],"iteration":880,"passed_time":1.062132997,"remaining_time":0.1434663185},
{"learn":[0.3423796273],"iteration":881,"passed_time":1.063125007,"remaining_time":0.1422321438},
{"learn":[0.3423796273],"iteration":882,"passed_time":1.064064046,"remaining_time":0.1409914987},
{"learn":[0.3423796273],"iteration":883,"passed_time":1.065339334,"remaining_time":0.1397956592},
{"learn":[0.3423796273],"iteration":884,"passed_time":1.066504559,"remaining_time":0.1385853381},
{"learn":[0.3423796273],"iteration":885,"passed_time":1.067659461,"remaining_time":0.1373737907},
{"learn":[0.3423796273],"iteration":886,"passed_time":1.068732043,"remaining_time":0.1361518837},
{"learn":[0.3423796273],"iteration":887,"passed_time":1.069827591,"remaining_time":0.1349332096},
{"learn":[0.3423796273],"iteration":888,"passed_time":1.071113867,"remaining_time":0.1337386268},
{"learn":[0.3423796273],"iteration":889,"passed_time":1.072276948,"remaining_time":0.1325286116},
{"learn":[0.3423796273],"iteration":890,"passed_time":1.073385933,"remaining_time":0.1313120838},
{"learn":[0.3423796273],"iteration":891,"passed_time":1.074524154,"remaining_time":0.130099337},
{"learn":[0.3423796273],"iteration":892,"passed_time":1.075579741,"remaining_time":0.1288768558},
{"learn":[0.3423796273],"iteration":893,"passed_time":1.076746444,"remaining_time":0.1276679229},
{"learn":[0.3423796273],"iteration":894,"passed_time":1.077954136,"remaining_time":0.126463893},
{"learn":[0.3423796273],"iteration":895,"passed_time":1.079237988,"remaining_time":0.1252686951},
{"learn":[0.3423796273],"iteration":896,"passed_time":1.080394823,"remaining_time":0.1240587144},
{"learn":[0.3423796273],"iteration":897,"passed_time":1.081499462,"remaining_time":0.1228429233},
{"learn":[0.3423796273],"iteration":898,"passed_time":1.082551643,"remaining_time":0.1216214861},
{"learn":[0.3423796273],"iteration":899,"passed_time":1.083623064,"remaining_time":0.1204025626},
{"learn":[0.3423796273],"iteration":900,"passed_time":1.084676712,"remaining_time":0.1191820138},
{"learn":[0.3423796273],"iteration":901,"passed_time":1.085689151,"remaining_time":0.1179573579},
{"learn":[0.3423796273],"iteration":902,"passed_time":1.086884749,"remaining_time":0.1167528468},
{"learn":[0.3423796273],"iteration":903,"passed_time":1.087954199,"remaining_time":0.1155349591},
{"learn":[0.3423796273],"iteration":904,"passed_time":1.088978942,"remaining_time":0.1143127066},
{"learn":[0.3423796273],"iteration":905,"passed_time":1.089978647,"remaining_time":0.1130882923},
{"learn":[0.3423796273],"iteration":906,"passed_time":1.090999005,"remaining_time":0.1118664912},
{"learn":[0.3423796273],"iteration":907,"passed_time":1.091940608,"remaining_time":0.1106371541},
{"learn":[0.3423796273],"iteration":908,"passed_time":1.093047271,"remaining_time":0.1094249743},
{"learn":[0.3423796273],"iteration":909,"passed_time":1.094078797,"remaining_time":0.1082055954},
{"learn":[0.3423796273],"iteration":910,"passed_time":1.095263175,"remaining_time":0.1070015616},
{"learn":[0.3423796273],"iteration":911,"passed_time":1.096341655,"remaining_time":0.1057873526},
{"learn":[0.3423796273],"iteration":912,"passed_time":1.097360371,"remaining_time":0.1045677462},
{"learn":[0.3423796273],"iteration":913,"passed_time":1.098397518,"remaining_time":0.1033503135},
{"learn":[0.3423796273],"iteration":914,"passed_time":1.099608594,"remaining_time":0.1021494322},
{"learn":[0.3423796273],"iteration":915,"passed_time":1.100670342,"remaining_time":0.1009348349},
{"learn":[0.3423796273],"iteration":916,"passed_time":1.101873605,"remaining_time":0.09973337974},
{"learn":[0.3423796273],"iteration":917,"passed_time":1.102979221,"remaining_time":0.09852319837},
{"learn":[0.3423796273],"iteration":918,"passed_time":1.104145993,"remaining_time":0.09731863483},
{"learn":[0.3423796273],"iteration":919,"passed_time":1.105190566,"remaining_time":0.09610352749},
{"learn":[0.3423796273],"iteration":920,"passed_time":1.106295594,"remaining_time":0.09489397605},
{"learn":[0.3423796273],"iteration":921,"passed_time":1.107462428,"remaining_time":0.09368988005},
{"learn":[0.3423796273],"iteration":922,"passed_time":1.108519618,"remaining_time":0.09247671789},
{"learn":[0.3423796273],"iteration":923,"passed_time":1.109666093,"remaining_time":0.0912712371},
{"learn":[0.3423796273],"iteration":924,"passed_time":1.110814124,"remaining_time":0.09006601007},
{"learn":[0.3423796273],"iteration":925,"passed_time":1.111862181,"remaining_time":0.08885291725},
{"learn":[0.3423796273],"iteration":926,"passed_time":1.11294991,"remaining_time":0.08764330465},
{"learn":[0.3423796273],"iteration":927,"passed_time":1.113986021,"remaining_time":0.0864299499},
{"learn":[0.3423796273],"iteration":928,"passed_time":1.115080764,"remaining_time":0.08522145773},
{"learn":[0.3423796273],"iteration":929,"passed_time":1.116200634,"remaining_time":0.08401510145},
{"learn":[0.3423796273],"iteration":930,"passed_time":1.117331962,"remaining_time":0.0828097802},
{"learn":[0.3423796273],"iteration":931,"passed_time":1.118375148,"remaining_time":0.08159818678},
{"learn":[0.3423796273],"iteration":932,"passed_time":1.119555168,"remaining_time":0.08039678054},
{"learn":[0.3423796273],"iteration":933,"passed_time":1.120993657,"remaining_time":0.07921368456},
{"learn":[0.3423796273],"iteration":934,"passed_time":1.122182543,"remaining_time":0.07801269014},
{"learn":[0.3423796273],"iteration":935,"passed_time":1.12334075,"remaining_time":0.07680962392},
{"learn":[0.3423796273],"iteration":936,"passed_time":1.124607155,"remaining_time":0.07561392823},
{"learn":[0.3423796273],"iteration":937,"passed_time":1.125615975,"remaining_time":0.07440105594},
{"learn":[0.3423796273],"iteration":938,"passed_time":1.126699771,"remaining_time":0.07319348885},
{"learn":[0.3423796273],"iteration":939,"passed_time":1.127770419,"remaining_time":0.07198534592},
{"learn":[0.3423796273],"iteration":940,"passed_time":1.128935738,"remaining_time":0.07078343095},
{"learn":[0.3423796273],"iteration":941,"passed_time":1.130116248,"remaining_time":0.06958252905},
{"learn":[0.3423796273],"iteration":942,"passed_time":1.131148906,"remaining_time":0.06837273343},
{"learn":[0.3423796273],"iteration":943,"passed_time":1.132188591,"remaining_time":0.06716372997},
{"learn":[0.3423796273],"iteration":944,"passed_time":1.133229669,"remaining_time":0.0659551659},
{"learn":[0.3423796273],"iteration":945,"passed_time":1.134309535,"remaining_time":0.06474917007},
{"learn":[0.3423796273],"iteration":946,"passed_time":1.135390893,"remaining_time":0.06354352408},
{"learn":[0.3423796273],"iteration":947,"passed_time":1.136505593,"remaining_time":0.06233996921},
{"learn":[0.3423796273],"iteration":948,"passed_time":1.137647156,"remaining_time":0.06113804524},
{"learn":[0.3423796273],"iteration":949,"passed_time":1.138888448,"remaining_time":0.05994149725},
{"learn":[0.3423796273],"iteration":950,"passed_time":1.140073281,"remaining_time":0.05874194615},
{"learn":[0.3423796273],"iteration":951,"passed_time":1.14116003,"remaining_time":0.05753748052},
{"learn":[0.3423796273],"iteration":952,"passed_time":1.142241949,"remaining_time":0.05633302371},
{"learn":[0.3423796273],"iteration":953,"passed_time":1.143439347,"remaining_time":0.05513439198},
{"learn":[0.3423796273],"iteration":954,"passed_time":1.144424519,"remaining_time":0.05392576266},
{"learn":[0.3423796273],"iteration":955,"passed_time":1.14561642,"remaining_time":0.05272711556},
{"learn":[0.3423796273],"iteration":956,"passed_time":1.14662801,"remaining_time":0.05152038078},
{"learn":[0.3423796273],"iteration":957,"passed_time":1.14781483,"remaining_time":0.05032173576},
{"learn":[0.3423796273],"iteration":958,"passed_time":1.148972063,"remaining_time":0.04912185045},
{"learn":[0.3423796273],"iteration":959,"passed_time":1.150060328,"remaining_time":0.04791918033},
{"learn":[0.3423796273],"iteration":960,"passed_time":1.151027037,"remaining_time":0.04671181525},
{"learn":[0.3423796273],"iteration":961,"passed_time":1.152301583,"remaining_time":0.04551711035},
{"learn":[0.3423796273],"iteration":962,"passed_time":1.153490344,"remaining_time":0.04431894366},
{"learn":[0.3423796273],"iteration":963,"passed_time":1.154550945,"remaining_time":0.04311601041},
{"learn":[0.3423796273],"iteration":964,"passed_time":1.15562306,"remaining_time":0.04191378973},
{"learn":[0.3423796273],"iteration":965,"passed_time":1.156799636,"remaining_time":0.04071551513},
{"learn":[0.3423796273],"iteration":966,"passed_time":1.157993753,"remaining_time":0.03951788403},
{"learn":[0.3423796273],"iteration":967,"passed_time":1.159137562,"remaining_time":0.03831859707},
{"learn":[0.3423796273],"iteration":968,"passed_time":1.160296748,"remaining_time":0.03711991659},
{"learn":[0.3423796273],"iteration":969,"passed_time":1.161477075,"remaining_time":0.03592197139},
{"learn":[0.3423796273],"iteration":970,"passed_time":1.162467859,"remaining_time":0.03471840156},
{"learn":[0.3423796273],"iteration":971,"passed_time":1.163642529,"remaining_time":0.03352056667},
{"learn":[0.3423796273],"iteration":972,"passed_time":1.164786937,"remaining_time":0.03232193967},
{"learn":[0.3423796273],"iteration":973,"passed_time":1.16611253,"remaining_time":0.03112826055},
{"learn":[0.3423796273],"iteration":974,"passed_time":1.167192341,"remaining_time":0.02992800874},
{"learn":[0.3423796273],"iteration":975,"passed_time":1.168411634,"remaining_time":0.02873143362},
{"learn":[0.3423796273],"iteration":976,"passed_time":1.169390181,"remaining_time":0.02752914449},
{"learn":[0.3423796273],"iteration":977,"passed_time":1.170468698,"remaining_time":0.02632956172},
{"learn":[0.3423796273],"iteration":978,"passed_time":1.171628265,"remaining_time":0.02513196483},
{"learn":[0.3423796273],"iteration":979,"passed_time":1.172715122,"remaining_time":0.02393296167},
{"learn":[0.3423796273],"iteration":980,"passed_time":1.173868909,"remaining_time":0.02273548346},
{"learn":[0.3423796273],"iteration":981,"passed_time":1.174956921,"remaining_time":0.02153688857},
{"learn":[0.3423796273],"iteration":982,"passed_time":1.176150958,"remaining_time":0.02034035227},
{"learn":[0.3423796273],"iteration":983,"passed_time":1.177471625,"remaining_time":0.01914588007},
{"learn":[0.3423796273],"iteration":984,"passed_time":1.178565717,"remaining_time":0.01794770127},
{"learn":[0.3423796273],"iteration":985,"passed_time":1.179615727,"remaining_time":0.01674910769},
{"learn":[0.3423796273],"iteration":986,"passed_time":1.180725257,"remaining_time":0.01555159913},
{"learn":[0.3423796273],"iteration":987,"passed_time":1.181964433,"remaining_time":0.01435584332},
{"learn":[0.3423796273],"iteration":988,"passed_time":1.183026947,"remaining_time":0.0131580348},
{"learn":[0.3423796273],"iteration":989,"passed_time":1.184272068,"remaining_time":0.01196234412},
{"learn":[0.3423796273],"iteration":990,"passed_time":1.185293677,"remaining_time":0.01076452381},
{"learn":[0.3423796273],"iteration":991,"passed_time":1.186317201,"remaining_time":0.009567074201},
{"learn":[0.3423796273],"iteration":992,"passed_time":1.187329443,"remaining_time":0.008369895371},
{"learn":[0.3423796273],"iteration":993,"passed_time":1.188312367,"remaining_time":0.007172911671},
{"learn":[0.3423796273],"iteration":994,"passed_time":1.189395459,"remaining_time":0.005976861603},
{"learn":[0.3423796273],"iteration":995,"passed_time":1.190482281,"remaining_time":0.004781053337},
{"learn":[0.3423796273],"iteration":996,"passed_time":1.191560735,"remaining_time":0.00358543852},
{"learn":[0.3423796273],"iteration":997,"passed_time":1.192671602,"remaining_time":0.002390123451},
{"learn":[0.3423796273],"iteration":998,"passed_time":1.193737042,"remaining_time":0.001194931974},
{"learn":[0.3423796273],"iteration":999,"passed_time":1.194687391,"remaining_time":0}
]}